Workbook

Sheet PA CAPA
B2: Programa de Ação 2026 com base no Plano Estratégico 2026
B5: Acordo entre Líder e Liderado
B6: Área: Postos, Região do Sisal | N6: Rota. Indicador RH
B7: Líder da Equipe | D7: Ingrid | N7: CLT | O7: EST | P7: R$
B8: Líder direto | D8: Viviane | N8: 14 | O8: 5 | P8: =230000/N8 -> 16428.571
B9: Substituto | D9: A definir | N9: 13 | O9: 4 | P9: =213000/N9 -> 16384.615
B10: Equipe | D10: Santa Luz: Liliane (coleta e atend) Quele Vitório (atend. e col.) Indiara(Coleta), Antony(Est. Coleta), Ítalo Henrique ( Estagiários atend. e col) Maria eduarda (atend e col) - estg vida ativa + suporte aos sabados de slc. UVL Valente: Irailma (coleta e atend), Ingredy ( estag. coleta e atend) COI Coité: Kailane (atende e col.), Alice (coleta e atend), Beatriz (estag. atende e coleta) Riachão do Jacuípe: Raiane (Atende e coleta)
B11: Foco | D11: Melhorar a infraestrutura, formar equipe e alcançar meta de faturamento
B12: Estratégias Delegadas e Resultados Pactuados
B13: Prioridade 1 | D13: Acompanhar indicadores de desempenho. | E13: Meta | F13: Peso | G13: Prazo Início | H13: Prazo Término | I13: Indicador | L13: Aferição
B14: Resultado 1.1 | D14: Alcançar Faturamento projetado | E14: 1 | F14: 0.06 | G14: 01.01 | H14: 31.12 | I14: % de alcance do fat. Projetado | L14: Cronograma Evolução Unidades
B15: Resultado 1.2 | D15: Indice de particular e convenios | E15: acomp | G15: 01.01 | H15: 31.12 | I15: acompanhar | L15: Cronograma Evolução Unidades
B16: Resultado 1.3 | D16: Indice de crescimento ao ano e com relação a meta | E16: 0.15 | G16: 01.01 | H16: 31.12 | I16: % de crescimento | L16: Cronograma Evolução Unidades
B17: Resultado 1.4 | D17: Pacientes, Exames, TK médio | E17: acomp | F17: 0.06 | G17: 01.01 | H17: 31.12 | I17: acompanhar | L17: Cronograma Evolução Unidades
B18: Resultado 1.5 | D18: Indice de exames por paciente | E18: % | G18: 01.01 | H18: 31.12 | I18: acompanhar | L18: Cronograma Evolução Unidades
B19: Resultado 1.6 | D19: Garantir o indice de novos pacientes | E19: ? | F19: 0.06 | G19: 01.01 | H19: 31.12 | I19: acompanhar | L19: Cronograma Evolução Unidades
B20: Resultado 1.7 | D20: Garantir o % NPS de satisfação do cliente por unidade | E20: 0.8 | F20: 0.06 | G20: 01.01 | H20: 31.12 | I20: % de satisfação | L20: Cronograma Evolução Unidades
B21: Resultado 1.8 | D21: Gerir e converter Orçamento registrado | E21: 0.75 | F21: 0.06 | G21: 01.01 | H21: 31.12 | I21: % de orçamentos convertidos | L21: Cronograma Evolução Unidades
B22: Resultado 1.9 | D22: Indice de pacientes perdidos | E22: ? | G22: 01.01 | H22: 31.12 | I22: acompanhar | L22: Cronograma Evolução Unidades
B23: Resultado 1.10 | D23: Indice de descontos | E23: % | G23: 01.01 | H23: 31.12 | I23: media por unidade | L23: Cronograma Evolução Unidades
B24: Resultado 1.11 | D24: indice de fluxo financeiro | E24: R$ | G24: 01.01 | H24: 31.12 | I24: R$ | L24: Cronograma Evolução Unidades
B25: Resultado 1.12 | D25: Indice de faturamento por colaborador | E25: 20k | F25: 0.06 | G25: 01.01 | H25: 31.12 | I25: acompanhar | L25: Cronograma Evolução Unidades
B26: Resultado 1.13 | D26: Ranking de medicos solicitantes | E26: acomp | F26: 0.06 | G26: 01.01 | H26: 31.12 | I26: acompanhar | L26: Cronograma Evolução Unidades
B27: Resultado 1.14 | D27: Medir produtividade (R$ e Qtd.) pacientes por recepcionista | E27: acomp | F27: 0.06 | G27: 01.01 | H27: 31.12 | I27: por unidade | L27: Cronograma Evolução Unidades
B28: Resultado 1.15 | D28: Acompanhar cortesias e cobertura | E28: acomp | G28: 01.01 | H28: 31.12 | I28: acompanhar | L28: Relatorio Smart
B29: Resultado 1.16 | D29: Acompanhar erro Internos de fechamento de caixa por recepcionistas | E29: 0 | F29: 0.06 | G29: 01.01 | H29: 31.12 | I29: % de erros | L29: Relatorio Smart
B30: Resultado 1.17 | D30: Reduzir indice de Guias em aberto, pendentes e canceladas | E30: 0 | F30: 0.06 | G30: 01.01 | H30: 31.12 | I30: acompanhar | L30: Relatorio Smart
B31: Resultado 1.18 | D31: Acompanhar Glosa Externa por recepcionista | E31: 0 | F31: 0.06 | G31: 01.01 | H31: 31.12 | I31: % de glosa externa | L31: Relatorio Smart
B32: Prioridade 2 | D32: Atrair, formar e reter talentos e equipes. | E32: Meta | F32: Peso | G32: Prazo Início | H32: Prazo Término | I32: Indicador | L32: Aferição
B33: Resultado 2.1 | D33: Realizar visitas mensais aos Postos de Coleta | E33: 1 | F33: 0.15 | G33: 01.01 | H33: 31.12 | I33: Qtd. de vezes por mês | L33: De segunda a sabado
B34: Resultado 2.2 | D34: Realizar as Reuniões de alinhamento com a equipe | E34: 4 | F34: 0.15 | G34: 01.01 | H34: 31.12 | I34: Reuniões trimestrais | L34: Ata das reuniões com a equipe.
B35: Resultado 2.3 | D35: Coordenar os Ciclos de treinamentos para as equipes dos postos. | E35: 12 | F35: 0.1 | G35: 01.01 | H35: 31.12 | I35: Qtd. Cursos Web e presenciais | L35: Registro.
B36: Resultado 2.4 | D36: Coordenar e aplicar as Avalições de Desempenho na rota | E36: 1 | G36: 01.01 | H36: 31.12 | I36: % dos liderados avaliados | L36: Avaliação de desempenho
B37: Prioridade 3 | E37: Meta | F37: Peso | G37: Prazo Início | H37: Prazo Término | I37: Indicador | L37: Aferição
B38: Resultado 3.1 | D38: Ações comerciais e de marketing | E38: 2 | G38: 01.01 | H38: 31.12
B39: Prioridade 4 | E39: Meta | F39: Peso | G39: Prazo Início | H39: Prazo Término | I39: Indicador | L39: Aferição
B40: Resultado 4.1 | D40: Identificar oportunidades de expanssão | E40: 2 | G40: 01.01 | H40: 31.12 | I40: Qud. De unidades abertas | L40: Unidades abertas
B41: Resultado 4.2 | D41: Reduzir custos com manutençoes de Ar condicionado, impressoras. | G41: 01.01 | H41: 31.12
B42: Resultado 4.3 | D42: Reforma das unidade (Pintura,piso, | G42: 01.01 | H42: 31.12
B43: Sistema de Comunicação e Informações
B44: Relatórios a Emitir | E44: Periodo | F44: Av. | G44: Destinatários | J44: Data de Entrega
B45: Rel. Mensal de avaliação da equipe | G45: Liderança | J45: Mensal e nos Acomp.
B46: Rel. de Visitas aos Postos | G46: Liderança | J46: Mensal e nos Acomp.
B47: Rel. Programar e Aplicar Avaliação de Desempenho nos colaboradores dos Postos | G47: Liderança | J47: Mensal e nos Acomp.
B48: Rel. de Indicadores do itens do Resultado 2.1 | G48: Liderança | J48: Mensal e nos Acomp.
B49: Rel. Realizar as Reformas dos Postos. (Jéssica) | G49: Liderança | J49: Mensal e nos Acomp.
B50: Rel. Cumprimento de CH contratual por recepcionistas | G50: Liderança | J50: Mensal e nos Acomp.
B51: Rel. Orçamento realizado Mensal e Trimestral e Com defasagem com o n OS.
B52: Relatórios a Receber | E52: Periodo | F52: Av. | G52: Remetente | J52: Data de Recebimento
B53: 1. Rel. de Erros por Recepcionista | E53: Mensal | G53: Jade | J53: Mensal e nos Acomp.
B54: 2. Rel. de Pesquisa de Satisfação | E54: Mensal | G54: Veronica | J54: Mensal e nos Acomp.
B55: 3. Rel de Controle de Horas | E55: Mensal | G55: Iane | J55: Mensal e nos Acomp.
B56: Reuniões Convocadas | E56: Periodo | F56: Av. | G56: Hora | J56: Participantes
B58: Gestão de Mudanças ISO9001/2015
B59: Na própria área | E59: Planejamento | M59: Data
B61: Nas demais área | E61: Planejamento | M61: Data
B63: Interrelações
B64: Fatores Críticos Identificados - Contribuições de Melhoria | I64: Responsável | L64: Prazo para Resolução
B66: Demandas Pactuadas com o Líder
B67: Recursos Humanos | E67: Quantidade | H67: Salário | J67: Total | L67: Data p/Contratação
B68: n/a
B69: Recursos Materiais | E69: Quantidade | H69: Preço | J69: Custo total | L69: Data p/Contratação
B70: n/a
B71: Capacitações e Qualificações | E71: Quantidade | H71: Preço | J71: Custo total | L71: Data p/ realização
B72: n/a
B73: Participação nos Resultados Gerados
B74: Premissas | H74: Valor base da Participação | J74: Pacto do Responsável pelo PA | L74: Pacto do Líder

Sheet 1. SANTA LUZ
B2: PROJEÇÃO POSTOS SANTA LUZ CENTRO
B5: 2021 | C5: JAN | D5: FEV | E5: MAR | F5: ABR | G5: MAI | H5: JUN | I5: JUL | J5: AGO | K5: SET | L5: OUT | M5: NOV | N5: DEZ
B6: meta 2021 | D6: 10000 | E6: 10000 | F6: 10000 | G6: 10000 | H6: 10000 | I6: 15000 | J6: 15000 | K6: 15000 | L6: 20000 | M6: 20000 | N6: 20000 | O6: =SUM(D6:N6) -> 155000
E7: 13000 | F7: 13000 | G7: 13000 | H7: 18000 | I7: 22000 | J7: 22000 | K7: 22000
B8: Convênio | C8: 456.21 | D8: 5261.87 | E8: 4169.69 | F8: 5637.42 | G8: 4377.69 | H8: 4835.07 | I8: 8954.85 | J8: 5327.83 | K8: 4460.3 | L8: 10921.05 | M8: 11667.51 | N8: 10490.07
B9: Particular | C9: 2938.36 | D9: 7555.5 | E9: 9639.19 | F9: 12714.53 | G9: 18482.37 | H9: 20441.2 | I9: 14911.63 | J9: 16666.7 | K9: 18080.49 | L9: 26318.46 | M9: 28898.34 | N9: 18391.68
B10: REALIZADO 2021 | C10: =C8+C9 -> 3394.57 | D10: =D8+D9 -> 12817.37 | E10: =E8+E9 -> 13808.88 | F10: =F8+F9 -> 18351.95 | G10: =G8+G9 -> 22860.06 | H10: =H8+H9 -> 25276.27 | I10: =I8+I9 -> 23866.48 | J10: =J8+J9 -> 21994.53 | ... N10: =N8+N9 -> 28881.75 | O10: =SUM(C10:N10) -> 271598.01
B11: base meta 2019
B12: ano anterior
B14: 2021 | C14: JAN | D14: FEV | E14: MAR | F14: ABR | G14: MAI | H14: JUN | I14: JUL | J14: AGO | K14: SET | L14: OUT | M14: NOV | N14: DEZ
B15: Pacientes | C15: 95 | D15: 101 | E15: 159 | F15: 162 | G15: 210 | H15: 182 | I15: =24+191 -> 215 | J15: =206+23 -> 229 | K15: =214+21 -> 235 | L15: =28+308 -> 336 | M15: =39+352 -> 391 | N15: 239
B16: Exames | C16: 1144 | D16: 774 | E16: 716 | F16: 900 | G16: 1173 | H16: 1274 | I16: =466+772 -> 1238 | J16: =444+969 -> 1413 | K16: =1108+417 -> 1525 | L16: =1423+646 -> 2069 | M16: =819+1493 -> 2312 | N16: 1680
B17: tk medio | C17: =C10/C15 -> 35.732316 | D17: =D10/D15 -> 126.90465 | E17: =E10/E15 -> 86.848302 | F17: =F10/F15 -> 113.28364 | G17: =G10/G15 -> 108.85743 | H17: =H10/H15 -> 138.8806 | I17: =I10/I15 -> 111.00688 | J17: =J10/J15 -> 96.045983 | ... N17: =N10/N15 -> 120.84414
B18: indice de satisfação | C18: 0.55 | D18: 0.6 | E18: 0.92 | F18: 0.83 | G18: 1 | H18: 1 | I18: 0.88 | J18: 0.82 | K18: 1 | L18: 0.8 | M18: 0.8
B20: 2022 | C20: JAN | D20: FEV | E20: MAR | F20: ABR | G20: MAI | H20: JUN | I20: JUL | J20: AGO | K20: SET | L20: OUT | M20: NOV | N20: DEZ
B21: meta 2022 35 MIL | C21: 20000 | D21: 20000 | E21: 23000 | F21: 23000 | G21: 23000 | H21: 20000 | I21: 20000 | J21: 30000 | K21: 30000 | L21: 35000 | M21: 35000 | N21: 30000 | O21: =SUM(C21:N21) -> 309000
B22: Convênio | C22: 6462.6 | D22: 7597.49 | E22: 10494.36 | F22: 9231.46 | G22: 11726.49 | H22: 3790.34 | I22: 10179.37 | J22: 15486.76 | K22: 9481.07 | L22: 6130.34 | M22: 13930.43 | N22: 15610.88
B23: Particular | C23: 24383.38 | D23: 34389.26 | E23: 26482.19 | F23: 17365.22 | G23: 24438.74 | H23: 23299.33 | I23: 22895.77 | J23: 27008.03 | K23: 28273.58 | L23: 33579.39 | M23: 36442.58 | N23: 21782.12
B24: REALIZADO 2022 | C24: =C22+C23 -> 30845.98 | D24: =D22+D23 -> 41986.75 | E24: =E22+E23 -> 36976.55 | F24: =F22+F23 -> 26596.68 | G24: =G22+G23 -> 36165.23 | H24: =H22+H23 -> 27089.67 | I24: =I22+I23 -> 33075.14 | J24: =J22+J23 -> 42494.79 | ... N24: =N22+N23 -> 37393 | O24: =SUM(C24:N24) -> 440461.18 | P24: =O24/O10 -> 1.6217393
B25: base meta 2022 | C25: =(C24/C21)-1 -> 0.542299 | D25: =(D24/D21)-1 -> 1.0993375 | E25: =(E24/E21)-1 -> 0.60767609 | F25: =(F24/F21)-1 -> 0.15637739 | G25: =(G24/G21)-1 -> 0.5724013 | H25: =(H24/H21)-1 -> 0.3544835 | I25: =(I24/I21)-1 -> 0.653757 | J25: =(J24/J21)-1 -> 0.416493 | ... N25: =(N24/N21)-1 -> 0.24643333
B26: ano anterior | F26: =(F24/F10)-1 -> 0.44925635 | G26: =(G24/G10)-1 -> 0.58202691 | H26: =(H24/H10)-1 -> 0.07174318 | I26: =(I24/I10)-1 -> 0.38584073 | J26: =(J24/J10)-1 -> 0.93206174 | K26: =(K24/K10)-1 -> 0.67494795 | L26: =(L24/L10)-1 -> 0.066333311 | M26: =(M24/M10)-1 -> 0.24175902 | N26: =(N24/N10)-1 -> 0.29469302
B27: Orçamento Registrado
B28: Orçamento Registrado | C28: 10000 | M28: 69082.47 | N28: =N29+N30 -> 38435.11
B29: Orçamento Convertido | C29: 2000 | M29: 39814.8 | N29: 22641.79
B30: Orçamento NÃO Convertido | C30: 8000 | M30: 29267.67 | N30: 15793.32
B31: % de conversão | C31: =C29/C28 -> 0.2 | D31: =D29/D28 -> #DIV/0! | E31: =E29/E28 -> #DIV/0! | F31: =F29/F28 -> #DIV/0! | G31: =G29/G28 -> #DIV/0! | H31: =H29/H28 -> #DIV/0! | I31: =I29/I28 -> #DIV/0! | J31: =J29/J28 -> #DIV/0! | ... N31: =N29/N28 -> 0.58909133
B33: 2022 - indicadores | C33: JAN | D33: FEV | E33: MAR | F33: ABR | G33: MAI | H33: JUN | I33: JUL | J33: AGO | K33: SET | L33: OUT | M33: NOV | N33: DEZ
B34: pacientes novos | I34: 110 | J34: 127 | K34: 108 | L34: 188 | M34: 151 | N34: 33
B35: pacientes | C35: =247+28 -> 275 | D35: 365 | E35: =285+29 -> 314 | F35: =32+202 -> 234 | G35: =36+296 -> 332 | H35: =256+25 -> 281 | I35: =232+37 -> 269 | J35: =280+55 -> 335 | K35: =29+277 -> 306 | L35: =29+386 -> 415 | M35: 438 | N35: 264
B36: exames | C36: =565+1200 -> 1765 | D36: 2097 | E36: =627+2028 -> 2655 | F36: =632+1527 -> 2159 | G36: =822+1456 -> 2278 | H36: =1338+354 -> 1692 | I36: =806+1368 -> 2174 | J36: =1166+2098 -> 3264 | K36: =680+2117 -> 2797 | L36: =573+2079 -> 2652 | M36: 5810 | N36: 3343
B37: tk medio | C37: =C24/C35 -> 112.1672 | D37: =D24/D35 -> 115.03219 | E37: =E24/E35 -> 117.75971 | F37: =F24/F35 -> 113.66103 | G37: =G24/G35 -> 108.93142 | H37: =H24/H35 -> 96.40452 | I37: =I24/I35 -> 122.95591 | J37: =J24/J35 -> 126.85012 | ... N37: =N24/N35 -> 141.64015
B38: indice de satisfação | C38: 1 | D38: 0.6 | E38: 0.92 | F38: 0.83 | G38: 1 | H38: 1 | I38: 1 | J38: 0.89 | K38: 0.94 | L38: 0.88 | M38: 0.88 | N38: 0.84
B40: 2023 | C40: JAN | D40: FEV | E40: MAR | F40: ABR | G40: MAI | H40: JUN | I40: JUL | J40: AGO | K40: SET | L40: OUT | M40: NOV | N40: DEZ
B41: meta 2023 | C41: 30000 | D41: 35000 | E41: 45000 | F41: 45000 | G41: 45000 | H41: 35000 | I41: 35000 | J41: 45000 | K41: 45000 | L41: 45000 | M41: 45000 | N41: 35000 | O41: =SUM(C41:N41) -> 485000 | P41: =(O41/O24)-1 -> 0.1011186
F42: 60000 | G42: 60000 | I42: boas energias | J42: 60000 | K42: 60000 | L42: 60000 | M42: 60000
B43: Convênio | C43: 6888.43 | D43: 16436.94 | E43: 25990.42 | F43: 23921.62 | G43: 13888.13 | H43: 17693.11 | I43: 22985.03 | J43: 17944.2 | K43: 10197.57 | L43: 12501.25 | M43: 19766.93 | N43: 8736.11
B44: Particular | C44: 28157.08 | D44: 36782.36 | E44: 35874.93 | F44: 35593.15 | G44: 38234.51 | H44: 31066.55 | I44: 33136.94 | J44: 46859.31 | K44: 37421.79 | L44: 43675.5 | M44: 49301.23 | N44: 28672.47
B45: REALIZADO 2023 | C45: =C43+C44 -> 35045.51 | D45: =D43+D44 -> 53219.3 | E45: =E43+E44 -> 61865.35 | F45: =F43+F44 -> 59514.77 | G45: =G43+G44 -> 52122.64 | H45: =H43+H44 -> 48759.66 | I45: =I43+I44 -> 56121.97 | J45: =J43+J44 -> 64803.51 | K45: 47619.36 | L45: =L43+L44 -> 56176.75 | M45: 69068.16 | N45: =N43+N44 -> 37408.58 | O45: =SUM(C45:N45) -> 641725.56 | P45: =O45/O24 -> 1.4569401
B46: base meta 2022 | C46: =(C45/C41)-1 -> 0.16818367 | D46: =(D45/D41)-1 -> 0.52055143 | E46: =(E45/E41)-1 -> 0.37478556 | F46: =(F45/F41)-1 -> 0.32255044 | G46: =(G45/G41)-1 -> 0.15828089 | H46: =(H45/H41)-1 -> 0.39313314 | I46: =(I45/I41)-1 -> 0.60348486 | J46: =(J45/J41)-1 -> 0.440078 | ... N46: =(N45/N41)-1 -> 0.068816571
B47: ano anterior | C47: =(C45/C24)-1 -> 0.13614513 | D47: =(D45/D24)-1 -> 0.26752606 | E47: =(E45/E24)-1 -> 0.67309687 | F47: =(F45/F24)-1 -> 1.2376767 | G47: =(G45/G24)-1 -> 0.44123624 | H47: =(H45/H24)-1 -> 0.79993555 | I47: =(I45/I24)-1 -> 0.69680219 | J47: =(J45/J24)-1 -> 0.52497541 | ... N47: =(N45/N24)-1 -> 0.00041665552
B49: Orçamento Registrado
B50: Orçamento Registrado | C50: =C51+C52 -> 53251.26 | D50: =D51+D52 -> 64856.89 | E50: =E51+E52 -> 81684.87 | F50: =F51+F52 -> 61329.72 | G50: =G51+G52 -> 90359.7 | H50: =H51+H52 -> 57655.28 | I50: =I51+I52 -> 61038.42 | J50: =J51+J52 -> 82203.8 | ... N50: =N51+N52 -> 51264.69
B51: Orçamento Convertido | C51: 30630.54 | D51: 40108.59 | E51: 40016.87 | F51: 36944.53 | G51: 43825.24 | H51: 32529.7 | I51: 36641.02 | J51: 47713.57 | K51: 45005 | L51: 46463 | M51: 59884.38 | N51: 33676.82
B52: Orçamento NÃO Convertido | C52: 22620.72 | D52: 24748.3 | E52: 41668 | F52: 24385.19 | G52: 46534.46 | H52: 25125.58 | I52: 24397.4 | J52: 34490.23 | K52: 25156.39 | L52: 24913.66 | M52: 29822.57 | N52: 17587.87
B53: % de conversão | C53: =C51/C50 -> 0.5752078 | D53: =D51/D50 -> 0.61841679 | E53: =E51/E50 -> 0.48989329 | F53: =F51/F50 -> 0.60239196 | G53: =G51/G50 -> 0.48500869 | H53: =H51/H50 -> 0.56421025 | I53: =I51/I50 -> 0.60029437 | J53: =J51/J50 -> 0.58043022 | ... N53: =N51/N50 -> 0.65692039
B55: Atualizado em: | C55: 45266 | D55: 45266 | E55: 45266 | F55: 45266 | G55: 45266 | H55: 45266 | I55: 45266 | J55: 45266 | K55: 45266 | L55: 45266 | M55: 45266
C56: 20680.33 | D56: 21127.68 | E56: 34187.25 | F56: 23101.51 | G56: 40242.01 | H56: 19774.82 | I56: 22639.41 | J56: 27664.82 | K56: 21841.29 | L56: 23698.4
B57: fluxo financeiro | C57: =C45+C52 -> 57666.23 | D57: =D45+D52 -> 77967.6 | E57: =E45+E52 -> 103533.35 | F57: =F45+F52 -> 83899.96 | G57: =G45+G52 -> 98657.1 | H57: =H45+H52 -> 73885.24 | I57: =I45+I52 -> 80519.37 | J57: =J45+J52 -> 99293.74 | ... M57: =M45+M52 -> 98890.73
B59: Indice de desconto | C59: 0.1189 | D59: 0.216 | E59: 0.14 | F59: 0.16 | G59: 0.1511 | H59: 0.14 | N59: 0.08
B60: Pacientes perdidos | C60: =C52/C70 -> 206.54944 | D60: =D52/D70 -> 199.96071 | E60: =E52/E70 -> 307.80196 | F60: =F52/F70 -> 174.1367 | G60: =G52/G70 -> 414.25357 | I60: =I52/I70 -> 178.67034 | J60: =J52/J70 -> 292.19307 | K60: =K52/K70 -> 241.42429 | L60: =L52/L70 -> 204.44752 | M60: =M52/M70 -> 237.04976 | N60: =N52/N70 -> 155.15149
B61: pacientes perdidos relatorio
B63: 2023 - indicadores | C63: JAN | D63: FEV | E63: MAR | F63: ABR | G63: MAI | H63: JUN | I63: JUL | J63: AGO | K63: SET | L63: OUT | M63: NOV | N63: DEZ
B64: pacientes novos | C64: 123 | D64: 157 | E64: 180 | F64: 151 | G64: 172 | H64: 152 | I64: 147 | J64: 185 | K64: 165 | L64: 134 | M64: 163 | N64: 98
B65: % | C65: =C64/C66 -> 0.384375 | D65: =D64/D66 -> 0.36511628 | E65: =E64/E66 -> 0.39387309 | F65: =F64/F66 -> 0.35529412 | G65: =G64/G66 -> 0.37068966 | H65: =H64/H66 -> 0.35185185 | I65: =I64/I66 -> 0.35766423 | J65: =J64/J66 -> 0.33697632 | ... M65: =M64/M66 -> 0.29690346
B66: pacientes | C66: 320 | D66: =57+373 -> 430 | E66: =383+74 -> 457 | F66: 425 | G66: 464 | H66: 432 | I66: 411 | J66: 549 | K66: 457 | L66: 461 | M66: 549 | N66: 330
B67: exames | C67: 5046 | D67: =2646+1243 -> 3889 | E67: =2600+1905 -> 4505 | F67: 5989 | G67: 5685 | H67: =3805+1268 -> 5073 | I67: 5119 | J67: 1722 | K67: 4286 | L67: 5907 | M67: 7411 | N67: 3687
B69: Média de exames | C69: =C67/C66 -> 15.76875 | D69: =D67/D66 -> 9.044186 | E69: =E67/E66 -> 9.8577681 | F69: =F67/F66 -> 14.091765 | G69: =G67/G66 -> 12.252155 | H69: =H67/H66 -> 11.743056 | I69: =I67/I66 -> 12.454988 | J69: =J67/J66 -> 3.136612 | K69: =K67/K66 -> 9.3785558 | M69: =M67/M66 -> 13.499089 | N69: =N67/N66 -> 11.172727
B70: TK medio | C70: =C45/C66 -> 109.51722 | D70: =D45/D66 -> 123.76581 | E70: =E45/E66 -> 135.37276 | F70: =F45/F66 -> 140.03475 | G70: =G45/G66 -> 112.33328 | H70: =H45/H66 -> 112.86958 | I70: =I45/I66 -> 136.54981 | J70: =J45/J66 -> 118.03918 | ... N70: =N45/N66 -> 113.35933
B72: indice de satisfação | C72: 0.9 | D72: 1 | E72: 1 | F72: 0.8 | G72: 0.87 | H72: 1 | I72: 0.88 | K72: 0.87 | L72: 0.91 | M72: 0.66 | N72: 1
B73: Qtd. | C73: 2 | D73: 2 | E73: 23 | F73: 15 | G73: 15 | I73: 18 | K73: 8 | L73: 12 | M73: 12 | N73: 5
B75: Raking Medicos Top5 | M75: nomes | N75: Iacira Magalhães
M76: nomes | N76: Ionei Matos
N77: Bianca Da Silva
N78: Danilo Madureira
N79: Orlando Dourado
F82: *rever com base na realidade
B83: 2024 | C83: JAN | D83: FEV | E83: MAR | F83: ABR | G83: MAI | H83: JUN | I83: JUL | J83: AGO | K83: SET | L83: OUT | M83: NOV | N83: DEZ
B84: meta 2024 | C84: 50000 | D84: 50000 | E84: 65000 | F84: 65000 | G84: 65000 | H84: 50000 | I84: 50000 | J84: 65000 | K84: 65000 | L84: 65000 | M84: 65000 | N84: 50000 | O84: =SUM(C84:N84) -> 705000 | P84: =O84/O45 -> 1.0986005
B85: meta com ações | J85: 75000 | K85: 75000 | L85: 75000
B86: Convênio | C86: 14336.84 | D86: 21005.54 | E86: 11119.33 | F86: 19123.84 | G86: 17420.32 | H86: 15441.92 | I86: 17147.98 | J86: 16456.43 | K86: 12129.63 | L86: 20057.15 | M86: 17622.46 | N86: 18520.04
B87: Particular | C87: 36835.28 | D87: 39503.16 | E87: 46012.01 | F87: 48397.71 | G87: 57183.35 | H87: 42079.66 | I87: 38398.12 | J87: 59555.02 | K87: 47783.14 | L87: 45262.98 | M87: 41035.4 | N87: 33363.99
B88: REALIZADO 2024 | C88: =C86+C87 -> 51172.12 | D88: =D86+D87 -> 60508.7 | E88: =E86+E87 -> 57131.34 | F88: =F86+F87 -> 67521.55 | G88: =G86+G87 -> 74603.67 | H88: =H86+H87 -> 57521.58 | I88: =I86+I87 -> 55546.1 | J88: =J86+J87 -> 76011.45 | ... N88: =N86+N87 -> 51884.03 | O88: =SUM(C88:N88) -> 735791.3
B89: % | C89: =C88/C84 -> 1.0234424 | D89: =D88/D84 -> 1.210174 | E89: =E88/E84 -> 0.87894369 | F89: =F88/F84 -> 1.0387931 | G89: =G88/G84 -> 1.1477488 | H89: =H88/H84 -> 1.1504316 | I89: =I88/I84 -> 1.110922 | J89: =J88/J84 -> 1.1694069 | ... O89: =O88/O84 -> 1.0436756
B90: base meta 2023 | C90: =(C88/C84)-1 -> 0.0234424 | D90: =(D88/D84)-1 -> 0.210174 | E90: =(E88/E84)-1 -> -0.12105631 | F90: =(F88/F84)-1 -> 0.038793077 | G90: =(G88/G84)-1 -> 0.14774877 | H90: =(H88/H84)-1 -> 0.1504316 | I90: =(I88/I84)-1 -> 0.110922 | J90: =(J88/J84)-1 -> 0.16940692 | ... N90: =(N88/N84)-1 -> 0.0376806
B91: ano anterior | C91: =(C88/C45)-1 -> 0.46016194 | D91: =(D88/D45)-1 -> 0.13696911 | E91: =(E88/E45)-1 -> -0.076521187 | F91: =(F88/F45)-1 -> 0.13453433 | G91: =(G88/G45)-1 -> 0.43131027 | H91: =(H88/H45)-1 -> 0.17969608 | I91: =(I88/I45)-1 -> -0.010261044 | J91: =(J88/J45)-1 -> 0.17295267 | ... N91: =(N88/N45)-1 -> 0.38695535
B93: Orçamento Registrado
B94: Orçamento Registrado | C94: =C96+C95 -> 61792.92 | D94: =D95+D96 -> 66623.69 | E94: =E95+E96 -> 88522.08 | F94: =F95+F96 -> 96584.5 | G94: =G95+G96 -> 113645.23 | H94: =H95+H95 -> 93268.4 | I94: =I95+I95 -> 87072.62 | J94: =J95+J95 -> 135916.48 | K94: =K95+K95 -> 101957.96 | L94: =L95+L95 -> 108468.26 | M94: =M95+M95 -> 84510.1 | N94: =N95+N95 -> 0
B95: Orçamento Convertido | C95: 42830.63 | D95: 45615.01 | E95: 53917.31 | F95: 54251.82 | G95: 66461.02 | H95: 46634.2 | I95: 43536.31 | J95: 67958.24 | K95: 50978.98 | L95: 54234.13 | M95: 42255.05
B96: Orçamento NÃO Convertido | C96: 18962.29 | D96: 21008.68 | E96: 34604.77 | F96: 42332.68 | G96: 47184.21 | H96: 29172.32 | I96: 30461.22 | J96: 49551.15 | K96: 46271.81 | L96: 40666.15 | M96: 32771.67
B97: % de conversão | C97: =C95/C94 -> 0.69313167 | D97: =D95/D94 -> 0.68466652 | E97: =E95/E94 -> 0.60908318 | F97: =F95/F94 -> 0.56170317 | G97: =G95/G94 -> 0.58481135 | H97: =H95/H94 -> 0.5 | I97: =I95/I94 -> 0.5 | J97: =J95/J94 -> 0.5 | ... N97: =N95/N94 -> #DIV/0!
B99: Atualizado em: | C99: 16.05.2024 | D99: 16.05.2024 | E99: 16.05.2024 | F99: 45461 | G99: 45572 | H99: 45572 | I99: 45572 | J99: 45572
B100: Orçamento NÃO Convertido | C100: 21504.68 | D100: 29120.02 | E100: 31937.44 | F100: 38207.34 | G100: 46540.56 | H100: 25886.19 | I100: 28317.67 | J100: 46565.9
B101: fluxo financeiro | C101: =C88+C96 -> 70134.41 | D101: =D88+D96 -> 81517.38 | E101: =E88+E96 -> 91736.11 | F101: =F88+F96 -> 109854.23 | G101: =G88+G96 -> 121787.88 | H101: =H88+H96 -> 86693.9 | I101: =I88+I96 -> 86007.32 | J101: =J88+J96 -> 125562.6 | ... N101: =N88+N96 -> 51884.03
B103: Indice de desconto | C103: 0.127 | D103: 0.1302 | E103: =6477.22/E87 -> 0.14077238 | F103: =6347.46/F87 -> 0.13115207 | G103: =7882.38/G87 -> 0.13784397 | H103: =5442.73/H87 -> 0.12934349 | I103: =4695.74/I87 -> 0.12229088 | J103: =4695.74/J87 -> 0.07884709 | K103: =6950.59/K87 -> 0.14546114 | L103: =6974.16/L87 -> 0.15408088 | M103: =6066.19/M87 -> 0.14782822
B104: Pacientes perdidos | C104: =C96/C113 -> 156.74646 | D104: =D96/D113 -> 149.99082 | E104: =E96/E113 -> 272.5675 | F104: =F96/F113 -> 341.06116 | G104: =G96/G113 -> 378.84653 | H104: =H96/H113 -> 229.74092 | I104: =I96/I113 -> 241.84233 | J104: =J96/J113 -> 383.31167 | ... N104: =N96/N113 -> #DIV/0!
B106: indicadores | C106: JAN | D106: FEV | E106: MAR | F106: ABR | G106: MAI | H106: JUN | I106: JUL | J106: AGO | K106: SET | L106: OUT | M106: NOV | N106: DEZ
B107: pacientes novos | C107: 135 | D107: 124 | E107: 116 | F107: 169 | G107: 188 | H107: 137 | I107: 120 | J107: 175 | K107: 128 | L107: 125 | M107: 99
B108: pacientes | C108: 423 | D108: 432 | E108: =406+44 -> 450 | F108: =74+470 -> 544 | G108: =527+72 -> 599 | H108: =395+58 -> 453 | I108: =56+385 -> 441 | J108: =59+529 -> 588 | K108: =58+463 -> 521 | L108: =61+467 -> 528 | M108: =389+65 -> 454
B109: pacientes dia | C109: =C108/22 -> 19.227273 | D109: =D108/22 -> 19.636364 | E109: =E108/22 -> 20.454545 | F109: =F108/22 -> 24.727273 | G109: =G108/22 -> 27.227273 | H109: =H108/22 -> 20.590909 | I109: =I108/22 -> 20.045455 | J109: =J108/22 -> 26.727273 | ... M109: =M108/22 -> 20.636364
B110: exames | C110: =3883+1234 -> 5117 | D110: 6755 | E110: =4774+898 -> 5672 | F110: =5066+1480 -> 6546 | G110: =6157+1397 -> 7554 | H110: =4484+1128 -> 5612 | I110: =1314+3983 -> 5297 | J110: =1200+6148 -> 7348 | K110: =1187+5038 -> 6225 | L110: =1441+5446 -> 6887 | M110: =4758+1468 -> 6226
B112: Média de exames | C112: =C110/C108 -> 12.096927 | D112: =D110/D108 -> 15.636574 | E112: =E110/E108 -> 12.604444 | F112: =F110/F108 -> 12.033088 | G112: =G110/G108 -> 12.611018 | H112: =H110/H108 -> 12.388521 | I112: =I110/I108 -> 12.011338 | J112: =J110/J108 -> 12.496599 | ... M112: =M110/M108 -> 13.713656
B113: TK medio | C113: =C88/C108 -> 120.97428 | D113: =D88/D108 -> 140.06644 | E113: =E88/E108 -> 126.95853 | F113: =F88/F108 -> 124.1205 | G113: =G88/G108 -> 124.54703 | H113: =H88/H108 -> 126.97921 | I113: =I88/I108 -> 125.95488 | J113: =J88/J108 -> 129.27117 | ... N113: =N88/N108 -> #DIV/0!
B115: indice de satisfação | D115: 0.83 | E115: 1 | F115: 1 | G115: 0.75 | H115: 0 | I115: 0.95 | J115: 0.92 | K115: 0.84 | L115: 0.92 | M115: 0.77
B116: Qtd. | D116: 6 | E116: 4 | F116: 3 | G116: 8 | H116: 0 | I116: 141 | J116: 205 | K116: 31 | L116: 169 | M116: 142
B118: Medicos | C118: IACIRA MAGALHAES | D118: IACIRA MAGALHÃES
C119: IONEI DE MATOS | D119: LUIZ DELFINO | E119: IACIRA MAGALHÃES | F119: IONEI MATOS | G119: IONEI MATOS | H119: IACIRA MAGALHAES | I119: IACIRA MAGALHAES | J119: IACIRA MAGALHAES | K119: IONEI MAGALHAES | L119: IONEI DE MATOS
C120: ROBSON CEDRAZ | D120: BIANCA DA SILVA | E120: BIANCA DA SILVA | F120: IACIRA MAGALHAES | G120: IACIRA MAGALHAES | H120: IONEI MATOS | I120: IONEI MATOS | J120: IONEI MATOS | K120: GEANNE MASCARENHAS | L120: JOAO ESTRELA
C121: LUIZ DELFINO | D121: VITÓRIA GONZAGA | E121: RAVENA MIRANDA | F121: LUIZ DELFINO | G121: BIANCA DE SILVA CARN | H121: BERNARDO JUNIOR | I121: BERNARDO JUNIOR | J121: VAGNER ANGELIS DE MO | K121: GRAZIELLE CARVALHO | L121: WILSON F SANTIAGO
E122: WILSON F. SANTIAGO | F122: BIANCA DA SILVA | G122: GRAZIELLE CARVALHO | H122: CISSA F. l. ARAUJO | I122: BIANCA DA SILVA CARNEIRO | J122: CARLA FREITAS | K122: IACIRA MAGALHAES | L122: SILVANIO P DA ROCHA
C123: SUS | E123: MARILIA PIO CARNEIRO | F123: BERNARDO JUNIOR | G123: ANDRE RICARDO | H123: BIANCA DE SILVA CARN | I123: CATARINA CRUZ | J123: RAVENA MIRANDA | K123: BIANCA DA SILVA | L123: DANILO MADUREIRA
...

Sheet 3. COITÉ 
B2: PROJEÇÃO POSTOS CONCEIÇÃO DO COITÉ
B5: 2020 | C5: JAN | D5: FEV | E5: MAR | F5: ABR | G5: MAI | H5: JUN | I5: JUL | J5: AGO | K5: SET | L5: OUT | M5: NOV | N5: DEZ
B6: meta 2020 | G6: 5000 | H6: 5000 | I6: 5000 | J6: 5000 | K6: 5000 | L6: 5000 | M6: 10000 | N6: 10000
B7: Nova meta corona virus | G7: 2500 | H7: =H6/2 -> 2500
B8: Convênio | G8: 113.15 | H8: 705.9 | I8: 1071.77 | J8: 2986.76 | K8: 3210.4 | L8: 2477.71 | M8: 713.93 | N8: 431.2
B9: Particular | G9: 210 | H9: 1411 | I9: 3948.82 | J9: 2050.8 | K9: 1952 | L9: 2677 | M9: 2704.5 | N9: 1523.25
B10: PROJEÇÃO 2020 | G10: =SUM(G8+G9) -> 323.15 | H10: =SUM(H8+H9) -> 2116.9 | I10: =SUM(I8+I9) -> 5020.59 | J10: =SUM(J8+J9) -> 5037.56 | K10: =SUM(K8+K9) -> 5162.4 | L10: =SUM(L8+L9) -> 5154.71 | M10: =SUM(M8+M9) -> 3418.43 | N10: 1954.45 | O10: =SUM(G10:N10) -> 28188.19 | P10: =O10/8 -> 3523.5237
B11: base meta 2020
B12: ano anterior
B14: 2021 | C14: JAN | D14: FEV | E14: MAR | F14: ABR | G14: MAI | H14: JUN | I14: JUL | J14: AGO | K14: SET | L14: OUT | M14: NOV | N14: DEZ
B15: meta 2021 | C15: 5000 | D15: 5000 | E15: 5000 | F15: 5000 | G15: 5000 | H15: 5000 | I15: 10000 | J15: 15000 | K15: 15000 | L15: 15000 | M15: 15000 | N15: 15000 | O15: =SUM(C15:N15) -> 115000
J16: 10000 | K16: 10000 | L16: 14000 | M16: 14000 | N16: 13000
B17: Convênio | C17: 1259.45 | D17: 3757.18 | E17: 2431.69 | F17: 1725.98 | G17: 1614.98 | H17: 1681.67 | I17: 3112.12 | J17: 6047.77 | K17: 9143.24 | L17: 5195.48 | M17: 6489.37 | N17: 6117.12
B18: Particular | C18: 1526.38 | D18: 1807.91 | E18: 3765.18 | F18: 4142.56 | G18: 3985 | H18: 5202.08 | I18: 3771 | J18: 4044 | K18: 4821 | L18: 4184.8 | M18: 2516.61 | N18: 3801
B19: REALIZADO 2021 | C19: =C17+C18 -> 2785.83 | D19: =D17+D18 -> 5565.09 | E19: =E17+E18 -> 6196.87 | F19: =F17+F18 -> 5868.54 | G19: =G17+G18 -> 5599.98 | H19: =H17+H18 -> 6883.75 | I19: =I17+I18 -> 6883.12 | J19: =J17+J18 -> 10091.77 | ... N19: =N17+N18 -> 9918.12 | O19: =SUM(C19:N19) -> 92143.57 | P19: =O19/10 -> 9214.357
B20: base meta 2020
B21: ano anterior
B23: 2020 | G23: MAI | H23: JUN | I23: JUL | J23: AGO | K23: SET | L23: OUT | M23: NOV | N23: DEZ
B24: Pacientes | G24: 4 | H24: 27 | I24: 48 | J24: 42 | K24: 33 | L24: 44
B25: Exames | G25: 12 | H25: 128 | I25: 288 | J25: 406 | K25: 353 | L25: 388
B26: tk medio | G26: =G24/G25 -> 0.33333333 | H26: =H24/H25 -> 0.2109375 | I26: =I24/I25 -> 0.16666667 | J26: =J24/J25 -> 0.10344828 | K26: =K24/K25 -> 0.093484419 | L26: =L24/L25 -> 0.11340206 | M26: =#REF!/M24 -> #REF! | N26: =#REF!/N24 -> #REF!
B28: 2021 | C28: JAN | D28: FEV | E28: MAR | F28: ABR | G28: MAI | H28: JUN | I28: JUL | J28: AGO | K28: SET | L28: OUT | M28: NOV | N28: DEZ
B29: pacientes | C29: 26 | D29: 31 | E29: 31 | F29: 46 | G29: 49 | H29: 58 | I29: =14+33 -> 47 | J29: =22+41 -> 63 | K29: =30+30 -> 60 | L29: =23+37 -> 60 | M29: =37+18 -> 55 | N29: 47
B30: exames | C30: 227 | D30: 415 | E30: 320 | F30: 377 | G30: 406 | H30: 476 | I30: =323+163 -> 486 | J30: =608+262 -> 870 | K30: =263+886 -> 1149 | L30: =224+461 -> 685 | M30: =138+564 -> 702 | N30: 832
B31: tk medio | C31: =C19/C29 -> 107.14731 | D31: =D19/D29 -> 179.51903 | E31: =E19/E29 -> 199.89903 | F31: =F19/F29 -> 127.57696 | G31: =G19/G29 -> 114.28531 | H31: =H19/H29 -> 118.68534 | I31: =I19/I29 -> 146.44936 | J31: =J19/J29 -> 160.18683 | ... N31: =N19/N29 -> 211.02383
B32: indice de satisfação | C32: 0.5 | D32: 0.66 | E32: 1 | F32: 0 | G32: 1 | H32: 1 | I32: 1 | J32: 1 | K32: 1 | L32: 0.83 | M32: 1
B34: 2022 | C34: JAN | D34: FEV | E34: MAR | F34: ABR | G34: MAI | H34: JUN | I34: JUL | J34: AGO | K34: SET | L34: OUT | M34: NOV | N34: DEZ
B35: meta 2022 | C35: 13000 | D35: 13000 | E35: 15000 | F35: 15000 | G35: 15000 | H35: 13000 | I35: 13000 | J35: 15000 | K35: 15000 | L35: 15000 | M35: 15000 | N35: 13000 | O35: =SUM(C35:N35) -> 170000
B36: Convênio | C36: 6293.87 | D36: 5397.23 | E36: 18224.06 | F36: 25305.65 | G36: 9558.5 | H36: 10126.11 | I36: 8836.06 | J36: 13533.77 | K36: 12468.35 | L36: 9836.46 | M36: 5043.31 | N36: 4695.23
B37: Particular | C37: 2275 | D37: 1857 | E37: 2412 | F37: 3192 | G37: 3230 | H37: 3705.46 | I37: 2114 | J37: 2018 | K37: 2630 | L37: 2080 | M37: 3380 | N37: 1960
B38: REALIZADO 2022 | C38: =C36+C37 -> 8568.87 | D38: =D36+D37 -> 7254.23 | E38: =E36+E37 -> 20636.06 | F38: =F36+F37 -> 28497.65 | G38: =G36+G37 -> 12788.5 | H38: =H36+H37 -> 13831.57 | I38: =I36+I37 -> 10950.06 | J38: =J36+J37 -> 15551.77 | ... N38: =N36+N37 -> 6655.23 | O38: =SUM(C38:N38) -> 160172.06 | P38: =O38+O19+O10 -> 280503.82
B39: CÁLCULO VARIÁVEL | C39: =(C38-C35)*0.01 -> -44.3113 | D39: =(D38-D35)*0.01 -> -57.4577 | E39: =(E38-E35)*0.01 -> 56.3606 | F39: =(F38-F35)*0.01 -> 134.9765 | G39: =(G38-G35)*0.01 -> -22.115 | H39: =(H38-H35)*0.01 -> 8.3157 | I39: =(I38-I35)*0.01 -> -20.4994 | J39: =(J38-J35)*0.01 -> 5.5177 | ... N39: =(N38-N35)*0.01 -> -63.4477
B40: base meta 2021
B41: ano anterior
B42: Orçamento Registrado
B43: Orçamento Registrado | C43: 10000 | M43: 6816.27
B44: Orçamento Convertido | C44: 2000 | M44: 3607.43
B45: Orçamento NÃO Convertido | C45: 8000 | M45: 3208.84
B46: % de conversão | C46: =C44/C43 -> 0.2 | D46: =D44/D43 -> #DIV/0! | E46: =E44/E43 -> #DIV/0! | F46: =F44/F43 -> #DIV/0! | G46: =G44/G43 -> #DIV/0! | H46: =H44/H43 -> #DIV/0! | I46: =I44/I43 -> #DIV/0! | J46: =J44/J43 -> #DIV/0! | ... N46: =N44/N43 -> #DIV/0!
B48: 2022 - indicadores | C48: JAN | D48: FEV | E48: MAR | F48: ABR | G48: MAI | H48: JUN | I48: JUL | J48: AGO | K48: SET | L48: OUT | M48: NOV | N48: DEZ
B49: pacientes novos | I49: 21 | J49: 29 | K49: 20 | L49: 20 | M49: 19 | N49: 16
B50: pacientes | C50: =25+20 -> 45 | D50: 50 | E50: =30+42 -> 72 | F50: =38+26 -> 64 | G50: =36+40 -> 76 | H50: =26+39 -> 65 | I50: =20+37 -> 57 | J50: =28+48 -> 76 | K50: =30+25 -> 55 | L50: =25+36 -> 61 | M50: 53 | N50: 50
B51: exames | C51: =127+581 -> 708 | D51: 519 | E51: =1346+177 -> 1523 | F51: =1429+218 -> 1647 | G51: =922+243 -> 1165 | H51: =223+786 -> 1009 | I51: =128+819 -> 947 | K51: =183+830 -> 1013 | L51: =845+101 -> 946 | M51: 735 | N51: 690
B52: tk medio | C52: =C38/C50 -> 190.41933 | D52: =D38/D50 -> 145.0846 | E52: =E38/E50 -> 286.61194 | F52: =F38/F50 -> 445.27578 | G52: =G38/G50 -> 168.26974 | H52: =H38/H50 -> 212.79338 | I52: =I38/I50 -> 192.10632 | J52: =J38/J50 -> 204.62855 | ... N52: =N38/N50 -> 133.1046
B53: indice de satisfação | C53: 1 | D53: 0.66 | E53: 1 | F53: 0 | G53: 1 | H53: 1 | I53: 1 | J53: 0.83 | K53: 0.5 | L53: 0.84 | M53: 1 | N53: 1
B55: 2023 | C55: JAN | D55: FEV | E55: MAR | F55: ABR | G55: MAI | H55: JUN | I55: JUL | J55: AGO | K55: SET | L55: OUT | M55: NOV | N55: DEZ
B56: meta 2023 | C56: 13000 | D56: 13000 | E56: 15000 | F56: 15000 | G56: 15000 | H56: 13000 | I56: 13000 | J56: 15000 | K56: 15000 | L56: 15000 | M56: 15000 | N56: 13000 | O56: =SUM(C56:N56) -> 170000
B57: Convênio | C57: 5896.76 | D57: 4369.11 | E57: 9090.15 | F57: 8387.39 | G57: 10561.29 | H57: 10930.46 | I57: 13999.29 | J57: 11088.9 | K57: 7471.45 | L57: 12092.1 | M57: 14645.44 | N57: 5042.03 | O57: =SUM(C57:N57) -> 113574.37
B58: Particular | C58: 3832 | D58: 4053 | E58: 3790.81 | F58: 4129.87 | G58: 6752.6 | H58: 2807 | I58: 4399 | J58: 4064 | K58: 4506 | L58: 3631 | M58: 4325 | N58: 3494.28 | O58: =SUM(C58:N58) -> 49784.56
B59: REALIZADO 2023 | C59: =C57+C58 -> 9728.76 | D59: =D57+D58 -> 8422.11 | E59: =E57+E58 -> 12880.96 | F59: =F57+F58 -> 12517.26 | G59: =G57+G58 -> 17313.89 | H59: =H57+H58 -> 13737.46 | I59: 18398.29 | J59: 15152.9 | K59: =K57+K58 -> 11977.45 | L59: =L57+L58 -> 15723.1 | M59: 18970.44 | N59: =N57+N58 -> 8536.31 | O59: =SUM(C59:N59) -> 163358.93 | P59: =O59+O40+O31 -> 163358.93
B60: base meta | C60: =(C59/C56)-1 -> -0.25163385 | D60: =(D59/D56)-1 -> -0.35214538 | E60: =(E59/E56)-1 -> -0.14126933 | F60: =(F59/F56)-1 -> -0.165516 | G60: =(G59/G56)-1 -> 0.15425933 | H60: =(H59/H56)-1 -> 0.056727692 | I60: =(I59/I56)-1 -> 0.41525308 | J60: =(J59/J56)-1 -> 0.010193333 | ... N60: =(N59/N56)-1 -> -0.34336077
B61: ano anterior | C61: =(C59/C38)-1 -> 0.13536091 | D61: =(D59/D38)-1 -> 0.16099297 | E61: =(E59/E38)-1 -> -0.37580333 | F61: =(F59/F38)-1 -> -0.56076168 | G61: =(G59/G38)-1 -> 0.35386402 | H61: =(H59/H38)-1 -> -0.0068039998 | I61: =(I59/I38)-1 -> 0.68019993 | J61: =(J59/J38)-1 -> -0.025647884 | ... N61: =(N59/N38)-1 -> 0.28264688
B63: Orçamento Registrado
B64: Orçamento Registrado | C64: =C65+C66 -> 18286.29 | D64: =D65+D66 -> 18128.38 | E64: =E65+E66 -> 13910.56 | F64: =F65+F66 -> 16576.95 | G64: =G65+G66 -> 18592.67 | H64: =H65+H66 -> 7506.73 | I64: =I65+I66 -> 10775.39 | J64: =J65+J66 -> 12523.2 | ... N64: =N65+N66 -> 10003.45
B65: Orçamento Convertido | C65: 4958.99 | D65: 5294.19 | E65: 4763.81 | F65: 4210.19 | G65: 9914.22 | H65: 2264.37 | I65: 6230.7 | J65: 4830.3 | K65: 5736.44 | L65: 4510.13 | M65: 5439.94 | N65: 4887.54
B66: Orçamento NÃO Convertido | C66: 13327.3 | D66: 12834.19 | E66: 9146.75 | F66: 12366.76 | G66: 8678.45 | H66: 5242.36 | I66: 4544.69 | J66: 7692.9 | K66: 9198.3 | L66: 3874.7 | M66: 6417.27 | N66: 5115.91
B67: % de conversão | C67: =C65/C64 -> 0.27118623 | D67: =D65/D64 -> 0.29203878 | E67: =E65/E64 -> 0.34245997 | F67: =F65/F64 -> 0.25397857 | G67: =G65/G64 -> 0.53323272 | H67: =H65/H64 -> 0.30164532 | I67: =I65/I64 -> 0.57823429 | J67: =J65/J64 -> 0.38570813 | ... N67: =N65/N64 -> 0.48858544
B69: Atualizado em: | C69: 45267 | D69: 45267 | E69: 45267 | F69: 45267 | G69: 45267 | H69: 45267 | I69: 45267 | J69: 45267 | K69: 45267 | L69: 45267 | M69: 45267
C70: 12887.3 | D70: 10992.47 | E70: 6873.25 | F70: 11968.97 | G70: 7608.46 | H70: 5208.34 | I70: 4199.92 | J70: 6435.21 | K70: 8468.36 | L70: 3076.38 | M70: 13327.3
B72: Indice de desconto | C72: 0.218 | D72: 0.22 | E72: 0.26 | F72: 0.3197 | G72: 0.285 | H72: % | I72: 0.37 | M72: 0.28 | N72: 0.113
B73: Pacientes perdidos | C73: =C66/C81 -> 87.672756 | D73: =D66/D81 -> 100.57534 | E73: =E66/E81 -> 40.475613 | F73: =F66/F81 -> 72.122292 | G73: =G66/G81 -> 52.129175 | H73: =H66/H81 -> 22.515024 | I73: =I66/I81 -> 23.466613 | J73: =J66/J81 -> 39.59943 | ... N73: =N66/N81 -> 31.164206
B75: 2023 - indicadores | C75: JAN | D75: FEV | E75: MAR | F75: ABR | G75: MAI | H75: JUN | I75: JUL | J75: AGO | K75: SET | L75: OUT | M75: NOV | N75: DEZ
B76: pacientes novos | C76: 22 | D76: 28 | E76: 19 | F76: 27 | G76: 43 | H76: 16 | I76: 41 | J76: 29 | K76: 23 | L76: 37 | M76: 27 | N76: 14
B77: pacientes | C77: 64 | D77: =30+36 -> 66 | E77: =30+27 -> 57 | F77: 73 | G77: 104 | H77: =24+35 -> 59 | I77: 95 | J77: 78 | K77: 81 | L77: 92 | M77: 98 | N77: 52
B78: exames | C78: 1030 | D78: =506+239 -> 745 | E78: =273+779 -> 1052 | F78: 1159 | G78: 1653 | H78: =884+305 -> 1189 | I78: 1767 | J78: 1364 | K78: 1143 | L78: 3778 | M78: 1694 | N78: 723
B80: Média de exames | C80: =C78/C77 -> 16.09375 | D80: =D78/D77 -> 11.287879 | E80: =E78/E77 -> 18.45614 | F80: =F78/F77 -> 15.876712 | G80: =G78/G77 -> 15.894231 | H80: =H78/H77 -> 20.152542 | I80: =I78/I77 -> 18.6 | J80: =J78/J77 -> 17.487179 | K80: =K78/K77 -> 14.111111 | M80: =M78/M77 -> 17.285714 | N80: =N78/N77 -> 13.903846
B81: TK medio | C81: =C59/C77 -> 152.01188 | D81: =D59/D77 -> 127.60773 | E81: =E59/E77 -> 225.98175 | F81: =F59/F77 -> 171.46932 | G81: =G59/G77 -> 166.47971 | H81: =H59/H77 -> 232.83831 | I81: =I59/I77 -> 193.66621 | J81: =J59/J77 -> 194.26795 | ... N81: =N59/N77 -> 164.15981
B83: Indice de satisfação | C83: 0.75 | D83: 1 | E83: 1 | F83: 1 | G83: 1 | H83: 1 | I83: 1 | K83: 1 | L83: 0.33 | M83: 0.75 | N83: 1
B84: Qtd. | D84: 1 | E84: 3 | F84: 4 | G84: 7 | I84: 6 | K84: 5 | L84: 3 | M84: 4 | N84: 1
B86: Raking Medicos Top5 | N86: Grazielle Carvalho
B87: 2024 | C87: JAN | D87: FEV | E87: MAR | F87: ABR | G87: MAI | H87: JUN | I87: JUL | J87: AGO | K87: SET | L87: OUT | M87: NOV | N87: DEZ
B88: meta 2024 | C88: =C59*1.15 -> 11188.074 | D88: =D59*1.15 -> 9685.4265 | E88: =E59*1.15 -> 14813.104 | F88: =F59*1.15 -> 14394.849 | G88: =G59*1.15 -> 19910.973 | H88: =H59*1.15 -> 15798.079 | I88: =I59*1.15 -> 21158.033 | J88: =J59*1.15 -> 17425.835 | ... N88: =N59*1.15 -> 9816.7565 | O88: =SUM(C88:N88) -> 187862.77
B89: Convênio | C89: 12393.64 | D89: 14089.96 | E89: 12520.64 | F89: 22838.38 | G89: 11845.65 | H89: 15833.08 | I89: 17086.09 | J89: 12286.43 | K89: 16834.43 | L89: 15541.06 | M89: 18525.69 | N89: 10834.1 | O89: =SUM(C89:N89) -> 180629.15
B90: Particular | C90: 3203 | D90: 5538 | E90: 7443 | F90: 5879 | G90: 4796 | H90: 5753 | I90: 6372 | J90: 5982.02 | K90: 7008.68 | L90: 10356.9 | M90: 6423 | N90: 4190.18 | O90: =SUM(C90:N90) -> 72944.78
B91: REALIZADO 2024 | C91: =C89+C90 -> 15596.64 | D91: =D89+D90 -> 19627.96 | E91: =E89+E90 -> 19963.64 | F91: =F89+F90 -> 28717.38 | G91: =G89+G90 -> 16641.65 | H91: =H89+H90 -> 21586.08 | I91: =I89+I90 -> 23458.09 | J91: =J89+J90 -> 18268.45 | ... N91: =N89+N90 -> 15024.28 | O91: =SUM(C91:N91) -> 253573.93 | P91: =O91+O72+O63 -> 253573.93
B92: base meta | C92: =(C91/C88)-1 -> 0.39404155 | D92: =(D91/D88)-1 -> 1.0265458 | E92: =(E91/E88)-1 -> 0.34770133 | F92: =(F91/F88)-1 -> 0.99497612 | G92: =(G91/G88)-1 -> -0.16419707 | H92: =(H91/H88)-1 -> 0.36637372 | I92: =(I91/I88)-1 -> 0.10870843 | J92: =(J91/J88)-1 -> 0.048354354 | ... N92: =(N91/N88)-1 -> 0.53047292
B93: ano anterior | C93: =(C91/C59)-1 -> 0.60314778 | D93: =(D91/D59)-1 -> 1.3305276 | E93: =(E91/E59)-1 -> 0.54985653 | F93: =(F91/F59)-1 -> 1.2942225 | G93: =(G91/G59)-1 -> -0.03882663 | H93: =(H91/H59)-1 -> 0.57132978 | I93: =(I91/I59)-1 -> 0.27501469 | J93: =(J91/J59)-1 -> 0.20560751 | K93: =(K91/K70)-1 -> 1.8155522 | L93: =(L91/L70)-1 -> 7.4183228 | M93: =(M91/M70)-1 -> 0.87199883 | N93: =(N91/N70)-1 -> #DIV/0!
B95: % | C95: =C91/C88 -> 1.3940415 | D95: =D91/D88 -> 2.0265458 | E95: =E91/E88 -> 1.3477013 | F95: =F91/F88 -> 1.9949761 | G95: =G91/G88 -> 0.83580293 | H95: =H91/H88 -> 1.3663737 | I95: =I91/I88 -> 1.1087084 | J95: =J91/J88 -> 1.0483544 | ... O95: =O91/O88 -> 1.3497828
B96: Orçamento Registrado
B97: Orçamento Registrado | C97: =C98+C99 -> 7831.71 | D97: =D98+D99 -> 11101.53 | E97: =E98+E99 -> 15937.65 | F97: =F98+F99 -> 17313.55 | G97: =G98+G99 -> 12081.03 | H97: =H98+H99 -> 12666.31 | I97: =I98+I99 -> 18994 | J97: =J98+J99 -> 17564.98 | ... M97: =M98+M99 -> 14642.89
B98: Orçamento Convertido | C98: 4562.67 | D98: 5051.57 | E98: 10128.85 | F98: 7055.66 | G98: 6205.68 | H98: 7546.14 | I98: 9497 | J98: 7830.62 | K98: 8442.77 | L98: 13617.14 | M98: 8028.6
B99: Orçamento NÃO Convertido | C99: 3269.04 | D99: 6049.96 | E99: 5808.8 | F99: 10257.89 | G99: 5875.35 | H99: 5120.17 | I99: 9497 | J99: 9734.36 | K99: 7673.84 | L99: 8605.09 | M99: 6614.29
B100: % de conversão | C100: =C98/C97 -> 0.58258924 | D100: =D98/D97 -> 0.45503368 | E100: =E98/E97 -> 0.6355297 | F100: =F98/F97 -> 0.40752243 | G100: =G98/G97 -> 0.51367143 | H100: =H98/H97 -> 0.59576467 | I100: =I98/I97 -> 0.5 | J100: =J98/J97 -> 0.44580865 | ... N100: =N98/N97 -> #DIV/0!
B101: fluxo financeiro | C101: =C91+C99 -> 18865.68 | D101: =D91+D99 -> 25677.92 | E101: =E91+E99 -> 25772.44 | F101: =F91+F99 -> 38975.27 | G101: =G91+G99 -> 22517 | H101: =H91+H99 -> 26706.25 | I101: =I91+I99 -> 32955.09 | J101: =J91+J99 -> 28002.81 | ... N101: =N91+N99 -> 15024.28
B102: Atualizado em: | C102: 16.05.2024 | D102: 16.05.2024 | E102: 16.05.2024 | F102: 18.06.2024 | G102: 07.10.2024 | H102: 07.10.2024 | I102: 07.10.2024 | J102: 07.10.2024 | K102: 07.10.2024
B103: Orçamento NÃO Convertido | C103: 6049.96 | D103: 6514.67 | E103: 6911.92 | F103: 7944.43 | G103: 5330.73 | H103: 5569.19 | I103: 9192.76 | J103: 8785.24 | K103: 7081.34
B105: Indice de desconto | C105: 0.0762 | D105: 0.1009 | E105: =1832.93/7443 -> 0.24626226 | F105: =1530.2/F90 -> 0.26028236 | G105: =884.73/G90 -> 0.18447248 | H105: =991.09/H90 -> 0.1722736 | I105: =1460.88/I90 -> 0.22926554 | J105: =1437.42/J90 -> 0.24029007 | K105: =1437.42/K90 -> 0.2050914 | L105: =2069.79/L90 -> 0.19984648 | M105: =1729.44/M90 -> 0.26925736
B106: Pacientes perdidos | C106: =C98/C114 -> 28.37656 | D106: =D98/D114 -> 29.854459 | E106: =E98/E114 -> 76.104733 | F106: =F98/F114 -> 30.465935 | G106: =G98/G114 -> 36.544251 | H106: =H98/H114 -> 42.998785 | I106: =I98/I114 -> 55.464405 | J106: =J98/J114 -> 49.293799 | K106: =K99/K114 -> 49.242633 | L106: =L99/L114 -> 52.830775 | M106: =M99/M114 -> 34.199928 | N106: =N99/N114 -> #DIV/0!
B108: indicadores | C108: JAN | D108: FEV | E108: MAR | F108: ABR | G108: MAI | H108: JUN | I108: JUL | J108: AGO | K108: SET | L108: OUT | M108: NOV | N108: DEZ
B109: pacientes novos | C109: 41 | D109: 50 | E109: 57 | F109: 40 | G109: 30 | H109: 38 | I109: 37 | J109: 44 | K109: 56 | L109: 41 | M109: 45
B110: pacientes | C110: =33+64 -> 97 | D110: 116 | E110: =82+68 -> 150 | F110: =53+71 -> 124 | G110: =45+53 -> 98 | H110: =57+66 -> 123 | I110: =75+62 -> 137 | J110: =48+67 -> 115 | K110: =75+78 -> 153 | L110: =72+87 -> 159 | M110: =71+58 -> 129 | N110: =51+38 -> 89
B111: exames | C111: =339+1397 -> 1736 | D111: 1824 | E111: =1360+769 -> 2129 | F111: =596+1950 -> 2546 | G111: =387+1134 -> 1521 | H111: =456+1456 -> 1912 | I111: =624+1742 -> 2366 | J111: =1021+543 -> 1564 | K111: =725+1587 -> 2312 | L111: =939+1497 -> 2436 | M111: =611+1807 -> 2418 | N111: =479+867 -> 1346
B112: pacientes dia | C112: =C110/22 -> 4.4090909 | D112: =D110/22 -> 5.2727273 | E112: =E110/22 -> 6.8181818 | F112: =F110/22 -> 5.6363636 | G112: =G110/22 -> 4.4545455 | H112: =H110/22 -> 5.5909091 | I112: =I110/22 -> 6.2272727 | J112: =J110/22 -> 5.2272727 | ... N112: =N110/22 -> 4.0454545
B113: Média de exames | C113: =C111/C110 -> 17.896907 | D113: =D111/D110 -> 15.724138 | E113: =E111/E110 -> 14.193333 | F113: =F111/F110 -> 20.532258 | G113: =G111/G110 -> 15.520408 | H113: =H111/H110 -> 15.544715 | I113: =I111/I110 -> 17.270073 | J113: =J111/J110 -> 13.6 | ... M113: =M111/M110 -> 18.744186
B114: TK medio | C114: =C91/C110 -> 160.7901 | D114: =D91/D110 -> 169.20655 | E114: =E91/E110 -> 133.09093 | F114: =F91/F110 -> 231.59177 | G114: =G91/G110 -> 169.81276 | H114: =H91/H110 -> 175.49659 | I114: =I91/I110 -> 171.22693 | J114: =J91/J110 -> 158.85609 | ... M114: =M91/M110 -> 193.4007
B116: Indice de satisfação | D116: 1 | E116: 1 | F116: 1 | G116: 0.67 | H116: 0 | I116: 0.97 | J116: 0.94 | K116: 0.9 | L116: 0.93 | M116: 0.93
B117: Qtd. | D117: 3 | E117: 3 | F117: 3 | G117: 3 | H117: 0 | I117: 65 | J117: 47 | K117: 58 | L117: 56 | M117: 55
B119: MÉDIOS | C119: CATHARYNE SANCHO
C120: MARILIA PIO | E120: FLAVIO KUDO | F120: ARY ALVES | G120: DIOGENES CARLOS | H120: ANDRE RICARDO | I120: ANDRE RICARDO | J120: DIOGENES CARLOS | K120: LEON FREITAS RIOS | L120: CATHARYNNE SANCHO
C121: MARCIA REBOUÇAS | E121: RITA DE CASSIA MARTINS | F121: WANDERSON DA SILVA | G121: RITA DE CASSIA MARTINS | H121: CATHARYNNE SABCHO | I121: AROLDO PORTUGAL | J121: CARLA FREITAS | K121: SIMONE PEREIRA | L121: MARILIA PIO
...

Sheet 4. VALENTE 
B1: PROJEÇÃO POSTOS VALENTE
B4: 2021 | C4: JAN | D4: FEV | E4: MAR | F4: ABR | G4: MAI | H4: JUN | I4: JUL | J4: AGO | K4: SET | L4: OUT | M4: NOV | N4: DEZ
B5: meta 2021 | M5: 5000 | N5: 5000
B6: Convênio | M6: 1562.81 | N6: 823.37
B7: Particular | M7: 3895.4 | N7: 3174
B8: REALIZADO 2021 | M8: =M6+M7 -> 5458.21 | N8: =N7+N6 -> 3997.37
B9: base meta
B11: 2021 | C11: JAN | D11: FEV | E11: MAR | F11: ABR | G11: MAI | H11: JUN | I11: JUL | J11: AGO | K11: SET | L11: OUT | M11: NOV | N11: DEZ
B12: pacientes | M12: =7+47 -> 54 | N12: 31
B13: exames | M13: =448+132 -> 580 | N13: 218
B14: tk medio | C14: =C8/C12 -> #DIV/0! | D14: =D8/D12 -> #DIV/0! | E14: =E8/E12 -> #DIV/0! | F14: =F8/F12 -> #DIV/0! | G14: =G8/G12 -> #DIV/0! | H14: =H8/H12 -> #DIV/0! | I14: =I8/I12 -> #DIV/0! | J14: =J8/J12 -> #DIV/0! | ... N14: =N8/N12 -> 128.94742
B15: indice de satisfação | L15: alimentar | M15: 0.8 | N15: alimentar
B18: 2022 | C18: JAN | D18: FEV | E18: MAR | F18: ABR | G18: MAI | H18: JUN | I18: JUL | J18: AGO | K18: SET | L18: OUT | M18: NOV | N18: DEZ
B19: meta 2022 | D19: 5000 | E19: 5000 | F19: 5000 | G19: 5000 | H19: 5000 | I19: 5000 | J19: 10000 | K19: 10000 | L19: 10000 | M19: 10000 | N19: 10000 | O19: =SUM(C19:N19) -> 80000
B20: Convênio | C20: 1555.71 | D20: 2908.27 | E20: 1526.85 | F20: 3834.66 | G20: 2247.78 | H20: 2418.97 | I20: 2641.18 | J20: 2386.03 | K20: 5877.92 | L20: 5034.3 | M20: 6293 | N20: 2980.1
B21: Particular | C21: 3563.6 | D21: 3235.2 | E21: 3664.2 | F21: 3330.2 | G21: 4629.88 | H21: 4507.2 | I21: 3807.7 | J21: 7884.42 | K21: 4748 | L21: 5556 | M21: 5414 | N21: 3950
B22: REALIZADO 2022 | C22: =C20+C21 -> 5119.31 | D22: =D20+D21 -> 6143.47 | E22: =E20+E21 -> 5191.05 | F22: =F20+F21 -> 7164.86 | G22: =G20+G21 -> 6877.66 | H22: =H20+H21 -> 6926.17 | I22: =I20+I21 -> 6448.88 | J22: =J20+J21 -> 10270.45 | ... N22: =N20+N21 -> 6930.1 | O22: =SUM(C22:N22) -> 93995.17
B23: base meta 2021
B24: ano anterior
B26: Orçamento Registrado
B27: Orçamento Registrado | C27: 10000 | M27: 14393.28 | N27: =N28+N29 -> 8296.35
B28: Orçamento Convertido | C28: 2000 | M28: 7652.82 | N28: 4604.12
B29: Orçamento NÃO Convertido | C29: 8000 | M29: 6740.46 | N29: 3692.23
B30: % de conversão | C30: =C28/C27 -> 0.2 | D30: =D28/D27 -> #DIV/0! | E30: =E28/E27 -> #DIV/0! | F30: =F28/F27 -> #DIV/0! | G30: =G28/G27 -> #DIV/0! | H30: =H28/H27 -> #DIV/0! | I30: =I28/I27 -> #DIV/0! | J30: =J28/J27 -> #DIV/0! | ... N30: =N28/N27 -> 0.5549573
B32: 2022 - indicadores | C32: JAN | D32: FEV | E32: MAR | F32: ABR | G32: MAI | H32: JUN | I32: JUL | J32: AGO | K32: SET | L32: OUT | M32: NOV | N32: DEZ
B33: pacientes novos | I33: 26 | J33: 34 | K33: 29 | L33: 39 | M33: 42 | N33: 33
B34: pacientes | C34: =7+35 -> 42 | D34: 47 | E34: =6+50 -> 56 | F34: =7+35 -> 42 | G34: =59+8 -> 67 | H34: =61+8 -> 69 | I34: =52+12 -> 64 | J34: =67+12 -> 79 | K34: =12+54 -> 66 | L34: =63+10 -> 73 | M34: 83 | N34: 58
B35: exames | C35: =154+120 -> 274 | D35: 260 | E35: =194+231 -> 425 | F35: =175+312 -> 487 | G35: =186+139 -> 325 | H35: =246+224 -> 470 | I35: =139+182 -> 321 | J35: =127+386 -> 513 | K35: =293+294 -> 587 | L35: =327+368 -> 695 | M35: 951 | N35: 513
B36: tk medio | C36: =C22/C34 -> 121.88833 | D36: =D22/D34 -> 130.71213 | E36: =E22/E34 -> 92.697321 | F36: =F22/F34 -> 170.5919 | G36: =G22/G34 -> 102.65164 | H36: =H22/H34 -> 100.37928 | I36: =I22/I34 -> 100.76375 | J36: =J22/J34 -> 130.0057 | ... N36: =N22/N34 -> 119.48448
B37: indice de satisfação | C37: 1 | D37: 0.66 | E37: 1 | F37: 1 | G37: 1 | H37: 1 | I37: 1 | J37: 1 | K37: 1 | L37: 1 | M37: 1 | N37: 1
B39: 2023 | C39: JAN | D39: FEV | E39: MAR | F39: ABR | G39: MAI | H39: JUN | I39: JUL | J39: AGO | K39: SET | L39: OUT | M39: NOV | N39: DEZ
B40: meta 2023 | C40: 10000 | D40: 10000 | E40: 15000 | F40: 15000 | G40: 15000 | H40: 10000 | I40: 10000 | J40: 15000 | K40: 15000 | L40: 15000 | M40: 15000 | N40: 10000 | O40: =SUM(C40:N40) -> 155000
B41: Convênio | C41: 4679.69 | D41: 2573.65 | E41: 4183.02 | F41: 9132.82 | G41: 14388.32 | H41: 4518.96 | I41: 4538.41 | J41: 2477 | K41: 4624.04 | L41: 13390.52 | M41: 6877.71 | N41: 1627.17
B42: Particular | C42: 5371 | D42: 3906 | E42: 6987 | F42: 3606 | G42: 6903 | H42: 5378 | I42: 4240.02 | J42: 4157.4 | K42: 5911 | L42: 5123 | M42: 8138 | N42: 12385
B43: REALIZADO 2023 | C43: =C41+C42 -> 10050.69 | D43: =D41+D42 -> 6479.65 | E43: =E41+E42 -> 11170.02 | F43: =F41+F42 -> 12738.82 | G43: =G41+G42 -> 21291.32 | H43: =H41+H42 -> 9896.96 | I43: 8778.43 | J43: 6634.4 | K43: =K41+K42 -> 10535.04 | L43: =L41+L42 -> 18513.52 | M43: 15015.71 | N43: =N41+N42 -> 14012.17 | O43: =SUM(C43:N43) -> 145116.73
B44: base meta 2022
B45: ano anterior | C45: =(C43/C22)-1 -> 0.96328997 | D45: =(D43/D22)-1 -> 0.054721517 | E45: =(E43/E22)-1 -> 1.1517843 | F45: =(F43/F22)-1 -> 0.77795798 | G45: =(G43/G22)-1 -> 2.0957215 | H45: =(H43/H22)-1 -> 0.42892248 | I45: =(I43/I22)-1 -> 0.36123327 | J45: =(J43/J22)-1 -> -0.35403025 | ... M45: =(M43/M22)-1 -> 0.28262663
B47: Orçamento Registrado
B48: Orçamento Registrado | C48: =C49+C50 -> 12067.48 | D48: =D49+D50 -> 7500.34 | E48: =E49+E50 -> 14576.68 | F48: =F49+F50 -> 7411.36 | G48: =G49+G50 -> 12849.76 | H48: =H49+H50 -> 10136.7 | I48: =I49+I50 -> 6135.85 | J48: =J49+J50 -> 8463.91 | ... N48: =N49+N50 -> 18523.04
B49: Orçamento Convertido | C49: 6246.6 | D49: 5157.64 | E49: 8728.06 | F49: 4720.46 | G49: 8623.77 | H49: 6184.86 | I49: 4232.02 | J49: 5273.48 | K49: 6638.16 | L49: 7150.06 | M49: 8769.52 | N49: 15660.35
B50: Orçamento NÃO Convertido | C50: 5820.88 | D50: 2342.7 | E50: 5848.62 | F50: 2690.9 | G50: 4225.99 | H50: 3951.84 | I50: 1903.83 | J50: 3190.43 | K50: 1722.21 | L50: 6738.32 | M50: 5396.49 | N50: 2862.69
B51: % de conversão | C51: =C49/C48 -> 0.51763914 | D51: =D49/D48 -> 0.68765416 | E51: =E49/E48 -> 0.59876872 | F51: =F49/F48 -> 0.63692224 | G51: =G49/G48 -> 0.67112304 | H51: =H49/H48 -> 0.61014531 | I51: =I49/I48 -> 0.68972025 | J51: =J49/J48 -> 0.62305483 | ... N51: =N49/N48 -> 0.84545247
B53: Atualizado em: | C53: 45267 | D53: 45267 | E53: 45267 | F53: 45267 | G53: 45267 | H53: 45267 | I53: 45267 | J53: 45267 | K53: 45267 | L53: 45267 | M53: 45267
C54: 5680.3 | D54: 2155.35 | E54: 5759.66 | F54: 3135.96 | G54: 3583.04 | H54: 3822.09 | I54: 1903.83 | J54: 1387045 | K54: 1722.21 | L54: 6548.72 | M54: 5396.49
B56: Indice de desconto | C56: 0.1917 | D56: 0.23 | E56: 0.21 | F56: 0.21 | G56: 0.2716 | H56: 0.27 | M56: 0.29 | N56: 0.27
B57: Pacientes perdidos | C57: =C50/C65 -> 44.015573 | D57: =D50/D65 -> 21.331291 | E57: =E50/E65 -> 44.505981 | F57: =F50/F65 -> 11.617991 | G57: =G50/G65 -> 13.496924 | H57: =H50/H65 -> 30.745975 | I57: =I50/I65 -> 14.31381 | J57: =J50/J65 -> 33.662441 | ... N57: =N50/N65 -> 19.612825
B59: indicadores | C59: JAN | D59: FEV | E59: MAR | F59: ABR | G59: MAI | H59: JUN | I59: JUL | J59: AGO | K59: SET | L59: OUT | M59: NOV | N59: DEZ
B60: pacientes novos | C60: 32 | D60: 24 | E60: 31 | F60: 26 | G60: 24 | H60: 31 | I60: 33 | J60: 40 | K60: 46 | L60: 48 | M60: 55 | N60: 61
B61: pacientes | C61: 76 | D61: =5+54 -> 59 | E61: =75+10 -> 85 | F61: 55 | G61: 68 | H61: 77 | I61: 66 | J61: 70 | K61: 86 | L61: 206 | M61: 97 | N61: 96
B62: exames | C62: 849 | D62: =193+205 -> 398 | E62: =361+298 -> 659 | F62: 908 | G62: 1032 | H62: 881 | I62: 683 | J62: 622 | K62: 863 | L62: 1197 | M62: 1077 | N62: 760
B64: Média de exames | C64: =C62/C61 -> 11.171053 | D64: =D62/D61 -> 6.7457627 | E64: =E62/E61 -> 7.7529412 | F64: =F62/F61 -> 16.509091 | G64: =G62/G61 -> 15.176471 | H64: =H62/H61 -> 11.441558 | I64: =I62/I61 -> 10.348485 | J64: =J62/J61 -> 8.8857143 | ... N64: =N62/N61 -> 7.9166667
B65: TK medio | C65: =C43/C61 -> 132.24592 | D65: =D43/D61 -> 109.82458 | E65: =E43/E61 -> 131.412 | F65: =F43/F61 -> 231.61491 | G65: =G43/G61 -> 313.10765 | H65: =H43/H61 -> 128.53195 | I65: =I43/I61 -> 133.00652 | J65: =J43/J61 -> 94.777143 | ... N65: =N43/N61 -> 145.9601
B67: Indice de satisfação | C67: 0.6 | D67: 0 | E67: 1 | F67: 1 | G67: 0.5 | H67: 0.8 | I67: 1 | K67: 0.85 | L67: 1 | M67: 1 | N67: 1
B68: Quant. Pesquisas | D68: 1 | E68: 5 | F68: 2 | G68: 2 | I68: 3 | K68: 7 | L68: 5 | M68: 1 | N68: 4
B70: Raking Medicos Top5 | N70: Simone Pereira
N71: Benvinda Matias
N72: Luiz Delfino
N73: Gelson Carneiro
N74: Glelson
B77: 2024 | C77: JAN | D77: FEV | E77: MAR | F77: ABR | G77: MAI | H77: JUN | I77: JUL | J77: AGO | K77: SET | L77: OUT | M77: NOV | N77: DEZ
B78: meta 2024 | C78: =C43*1.15 -> 11558.293 | D78: =D43*1.15 -> 7451.5975 | E78: =E43*1.15 -> 12845.523 | F78: =F43*1.15 -> 14649.643 | G78: 20000 | H78: =H43*1.15 -> 11381.504 | I78: =I43*1.15 -> 10095.194 | J78: =J43*1.15 -> 7629.56 | K78: =K43*1.15 -> 12115.296 | L78: =L43*1.15 -> 21290.548 | M78: =M43*1.15 -> 17268.066 | N78: =N43*1.15 -> 16113.995 | O78: =SUM(C78:N78) -> 162399.22
B79: Convênio | C79: 6745.27 | D79: 7499.69 | E79: 8140.09 | F79: 8455.19 | G79: 11660 | H79: 8883.51 | I79: 12136.27 | J79: 5840.96 | K79: 4106.62 | L79: 11713.12 | M79: 10041.34 | N79: 5520.36
B80: Particular | C80: 8572 | D80: 7631 | E80: 5172 | F80: 11015 | G80: 7549.3 | H80: 8661 | I80: 11224 | J80: 9492 | K80: 9972 | L80: 7542 | M80: 9558 | N80: 7542
B81: REALIZADO 2024 | C81: =C80+C79 -> 15317.27 | D81: =D79+D80 -> 15130.69 | E81: =E79+E80 -> 13312.09 | F81: =F79+F80 -> 19470.19 | G81: =G79+G80 -> 19209.3 | H81: =H79+H80 -> 17544.51 | I81: =I79+I80 -> 23360.27 | J81: =J79+J80 -> 15332.96 | K81: =K79+K80 -> 14078.62 | ... N81: =N79+N80 -> 13062.36 | O81: =SUM(C81:N81) -> 204672.72
B82: base meta
B83: ano anterior | C83: =(C81/C43)-1 -> 0.52400183 | D83: =(D81/D43)-1 -> 1.3351091 | E83: =(E81/E43)-1 -> 0.19176958 | F83: =(F81/F43)-1 -> 0.52841393 | G83: =(G81/G43)-1 -> -0.097787267 | H83: =(H81/H43)-1 -> 0.77271708 | I83: =(I81/I43)-1 -> 1.6610989 | J83: =(J81/J43)-1 -> 1.3111299 | ... N83: =(N81/N43)-1 -> -0.067784647
B85: % | C85: =C81/C78 -> 1.325219 | D85: =D81/D78 -> 2.0305297 | E85: =E81/E78 -> 1.0363214 | F85: =F81/F78 -> 1.3290556 | G85: =G81/G78 -> 0.960465 | H85: =H81/H78 -> 1.5414931 | I85: =I81/I78 -> 2.313999 | J85: =J81/J78 -> 2.0096781 | ... O85: =O81/O78 -> 1.260306
B86: Orçamento Registrado
B87: Orçamento Registrado | C87: =C88+C89 -> 15830.53 | D87: =D88+D89 -> 5937.9 | E87: =E88+E89 -> 12392.8 | F87: =F88+F89 -> 22949.39 | G87: =G88+G89 -> 22080.55 | H87: =H88+H89 -> 17580.74 | I87: =I88+I89 -> 22616.36 | J87: =J88+J89 -> 19528.5 | ... N87: =N88+N89 -> 0
B88: Orçamento Convertido | C88: 12251.96 | D88: 2096.95 | E88: 6291.49 | F88: 16695.58 | G88: 15138.52 | H88: 10987.95 | I88: 15585.51 | J88: 11526.59 | K88: 12838.95 | L88: 9535.91 | M88: 13566.71
B89: Orçamento NÃO Convertido | C89: 3578.57 | D89: 3840.95 | E89: 6101.31 | F89: 6253.81 | G89: 6942.03 | H89: 6592.79 | I89: 7030.85 | J89: 8001.91 | K89: 11867.83 | L89: 6627.35 | M89: 9231.43
B90: % de conversão | C90: =C88/C87 -> 0.77394503 | D90: =D88/D87 -> 0.35314674 | E90: =E88/E87 -> 0.507673 | F90: =F88/F87 -> 0.72749559 | G90: =G88/G87 -> 0.6856043 | H90: =H88/H87 -> 0.62499929 | I90: =I88/I87 -> 0.68912548 | J90: =J88/J87 -> 0.59024451 | ... N90: =N88/N87 -> #DIV/0!
B91: fluxo financeiro | C91: =C81+C89 -> 18895.84 | D91: =D81+D89 -> 18971.64 | E91: =E81+E89 -> 19413.4 | F91: =F81+F89 -> 25724 | G91: =G81+G89 -> 26151.33 | H91: =H81+H89 -> 24137.3 | I91: =I81+I89 -> 30391.12 | J91: =J81+J89 -> 23334.87 | ... N91: =N81+N89 -> 13062.36
B92: Atualizado em: | C92: 16.05.2024 | D92: 16.05.2024 | E92: 16.05.2024 | F92: 18.06.2024 | G92: 07.10.2024 | H92: 07.10.2024 | I92: 07.10.2024 | J92: 07.10.2024 | K92: 07.10.2024
B93: Orçamento NÃO Convertido | C93: 3840.94 | D93: 3733.87 | E93: 5311.21 | F93: 4826.11 | G93: 7664.03 | H93: 5491.67 | I93: 6350.089 | J93: 7407.1 | K93: 11643.76
B95: Indice de desconto | C95: =4158.87/36043.7 -> 0.1153841 | D95: =4158.87/36043.7 -> 0.1153841 | E95: =1429.5/5172 -> 0.27639211 | F95: =4158.87/36043.7 -> 0.1153841 | G95: =3549.61/G80 -> 0.47019061 | H95: =2781.66/H80 -> 0.32117077 | I95: =3322.79/I80 -> 0.2960433 | J95: =3322.79/J80 -> 0.35006216 | K95: =3322.79/K80 -> 0.33321199 | L95: =3322.79/L80 -> 0.44057147 | M95: =3322.79/M80 -> 0.3476449 | N95: =3322.79/N80 -> 0.44057147
B96: Pacientes perdidos | C96: =C89/C104 -> 24.063865 | D96: =D89/D104 -> 109.6639 | E96: =E89/E104 -> 47.207834 | F96: =F89/F104 -> 48.179884 | G96: =G89/G104 -> 58.906409 | H96: =H89/H104 -> 35.698635 | I96: =I89/I104 -> 43.942305 | J96: =J89/J104 -> 88.718988 | ... N96: =N89/N104 -> #DIV/0!
B98: indicadores | C98: JAN | D98: FEV | E98: MAR | F98: ABR | G98: MAI | H98: JUN | I98: JUL | J98: AGO | K98: SET | L98: OUT | M98: NOV | N98: DEZ
B99: pacientes novos | C99: 49 | D99: 124 | E99: 49 | F99: 84 | G99: 88 | H99: 41 | I99: 62 | J99: 47 | K99: 48 | L99: 54 | M99: 68
B100: pacientes | C100: =80+23 -> 103 | D100: 432 | E100: =80+23 -> 103 | F100: =32+118 -> 150 | G100: =142+21 -> 163 | H100: =82+13 -> 95 | I100: =28+118 -> 146 | J100: =19+151 -> 170 | K100: =109+19 -> 128 | L100: =96+35 -> 131 | M100: =40+128 -> 168
B101: exames | C101: =696+350 -> 1046 | D101: 6755 | E101: =476+498 -> 974 | F101: =965+485 -> 1450 | G101: =1172+468 -> 1640 | H101: =414+607 -> 1021 | I101: =725+919 -> 1644 | J101: =399+951 -> 1350 | K101: =214+997 -> 1211 | L101: =744+655 -> 1399 | M101: =587+1110 -> 1697
B102: pacientes dia | C102: =C100/22 -> 4.6818182 | D102: =D100/22 -> 19.636364 | E102: =E100/22 -> 4.6818182 | F102: =F100/22 -> 6.8181818 | G102: =G100/22 -> 7.4090909 | H102: =H100/22 -> 4.3181818 | I102: =I100/22 -> 6.6363636 | J102: =J100/22 -> 7.7272727 | ... N102: =N100/22 -> 0
B103: Média de exames | C103: =C101/C100 -> 10.15534 | D103: =D101/D100 -> 15.636574 | E103: =E101/E100 -> 9.4563107 | F103: =F101/F100 -> 9.6666667 | G103: =G101/G100 -> 10.06135 | H103: =H101/H100 -> 10.747368 | I103: =I101/I100 -> 11.260274 | J103: =J101/J100 -> 7.9411765 | ... M103: =M101/M100 -> 10.10119
B104: TK medio | C104: =C81/C100 -> 148.71136 | D104: =D81/D100 -> 35.024745 | E104: =E81/E100 -> 129.24359 | F104: =F81/F100 -> 129.80127 | G104: =G81/G100 -> 117.84847 | H104: =H81/H100 -> 184.67905 | I104: =I81/I100 -> 160.00185 | J104: =J81/J100 -> 90.193882 | ... N104: =N81/N100 -> #DIV/0!
B106: Indice de satisfação | D106: 0.75 | E106: 1 | F106: 0 | G106: 1 | H106: 0 | I106: 0.94 | J106: 0.95 | K106: 0.8 | L106: 1 | M106: 0.86
B107: Quant. Pesquisas | D107: 4 | E107: 1 | F107: 4 | G107: 1 | H107: 0 | I107: 49 | J107: 37 | K107: 4 | L107: 34 | M107: 44
B109: MÉDICOS
C110: LUIZ DELFINO | E110: LUIZ DELFINO | F110: LUIZ DELFINO | G110: LUIZ DELFINO | H110: LUIZ DELFINO | I110: BENVINDA MATIAS | J110: IONEI DE MATOS | K110: IACIRA MAGALHAES | L110: LUIZ DELFINO
C111: ZENON NUNES | E111: MARIA LUZANETE | F111: BIANCCA MOREIRA | G111: AGENOR PAIVA JUNIOR | H111: MARIA LUZANETE | I111: LUIZ DELFINO | J111: GLEUCIANA T.B. | K111: BENVINDA MATIAS | L111: IANE MACEDO ARAUJO
C112: ALONSO ARAUJO | E112: RICARDO SOBRAL | F112: IONE MACEDO | G112: DANILO MADUREIRA | H112: JOAO ESTRELA | I112: GRAZIELLE CARVALHO | J112: LUIZ DELFINO | K112: IONEI DE MATOS | L112: IONEI DE MATOS
E113: GELSON CARNEIRO | F113: RICARDO SOBRAL | G113: ANTONIO NUNES | H113: GENOVIEVE MARINE | I113: LAIS MOTA | J113: BENVINDA MATIAS | K113: RITA CRISTINA | L113: PATRICIA BACELAR
E114: LAIS MOTA | F114: GELSON CARNEIRO | G114: ACLIVIA LOPES | H114: GRAZIELLE CARVALHO | I114: JOSE NILTON | J114: BERANRDO JUNIOR | K114: CISSA F L ARAUJO | L114: BENVINDA MATIAS
E115: GLAUCIANA T.B. | F115: GLAUCIANA T.B | G115: ANDRE VIEIRA LUZ | H115: LAILLA DE ALMEIDA | I115: JOAO ESTRELA | J115: MARCIO SOUZA NASCIEMNTO | K115: MAURICIO FERREIRA | L115: LOHANA ALMEIDA
E116: BENVINDA MATIAS | F116: IONEI DE MATOS | G116: ENIO HENRIQUE RIOS | H116: ZENON NUNES | I116: GELSON CARNEIRO | J116: JOSE NILTON | K116: IANE MACEDO | L116: ELAINE OLIVEIRA
E117: IONEI DE MATOS | F117: MARIALUZANETE | G117: RICARDO MIRANDA | H117: JAILTON C. ARAUJO | I117: EDUADO DOURADO | J117: CLARISSA GONCALVES | K117: JAILTON C ARAUJO | L117: TIANA CARNEIRO
E118: CISSA F. L. ARAUJO | F118: ENIO HENRIQUE RIOS | G118: ELAINE OLIVEIRA | H118: DANILO MADUREIR | I118: RITA CRISTINA | J118: JOILMA O. RIBEIRO | K118: AUGUSTO CESAR | L118: FLAVIO KUDO
E119: IACIRA MAGALHAES | F119: CISSA F. L. ARAUJO | G119: GLAUCIANE T.B. | H119: YARITZA HECHOVARRIA | I119: IONEI DE MATOS | J119: ISAAC M PIMENTEL | K119: ALMIR FERREIRA | L119: JOSE NILTON
K120: ACLIVIA LOPES | L120: MILLENE REIS
B121: Irailma
B122: R$ atend | K122: 13109.94
...

Sheet 2. RIAÇHÃO
B2: 2025 | C2: JAN | D2: FEV | E2: MAR | F2: ABR | G2: MAI | H2: JUN | I2: JUL | J2: AGO | K2: SET | L2: OUT | M2: NOV | N2: DEZ
B3: meta 2025 | J3: 12000 | K3: 12000 | L3: 12000 | M3: 12000 | N3: 12000 | O3: =SUM(C3:N3) -> 60000
B4: Convênio | K4: 189 | M4: 7185.99
B5: Particular | K5: 6881.3 | M5: 5095
B6: REALIZADO 2025 | G6: 6697.07 | H6: 7729.92 | I6: =2584.33+7750 -> 10334.33 | J6: 7206 | K6: 7050 | L6: 7317 | M6: 12292 | O6: =SUM(C6:N6) -> 58626.32

Sheet CONSOLIDADO
B2: 2025 | C2: JAN | D2: FEV | E2: MAR | F2: ABR | G2: MAI | H2: JUN | I2: JUL | J2: AGO | K2: SET | L2: OUT | M2: NOV | N2: DEZ
B3: meta 2025 | C3: ='1. SANTA LUZ'!C162+'2. RIAÇHÃO'!C3+'3. COITÉ '!C156+'4. VALENTE '!C138 -> 110551 | D3: ='1. SANTA LUZ'!D162+'2. RIAÇHÃO'!D3+'3. COITÉ '!D156+'4. VALENTE '!D138 -> 114972.45 | E3: ='1. SANTA LUZ'!E162+'2. RIAÇHÃO'!E3+'3. COITÉ '!E156+'4. VALENTE '!E138 -> 113267.09 | F3: ='1. SANTA LUZ'!F162+'2. RIAÇHÃO'!F3+'3. COITÉ '!F156+'4. VALENTE '!F138 -> 130415.71 | G3: ='1. SANTA LUZ'!G162+'2. RIAÇHÃO'!G3+'3. COITÉ '!G156+'4. VALENTE '!G138 -> 141228.59 | H3: ='1. SANTA LUZ'!H162+'2. RIAÇHÃO'!H3+'3. COITÉ '!H156+'4. VALENTE '!H138 -> 120000.18 | I3: ='1. SANTA LUZ'!I162+'2. RIAÇHÃO'!I3+'3. COITÉ '!I156+'4. VALENTE '!I138 -> 128841.11 | J3: ='1. SANTA LUZ'!J162+'2. RIAÇHÃO'!J3+'3. COITÉ '!J156+'4. VALENTE '!J138 -> 150641.62 | ... N3: ='1. SANTA LUZ'!N162+'2. RIAÇHÃO'!N3+'3. COITÉ '!N156+'4. VALENTE '!N138 -> 119299.64 | O3: =SUM(C3:N3) -> 1586983.6
B4: Convênio | C4: ='1. SANTA LUZ'!C163+'2. RIAÇHÃO'!C4+'3. COITÉ '!C157+'4. VALENTE '!C139 -> 51873.05 | D4: ='1. SANTA LUZ'!D163+'2. RIAÇHÃO'!D4+'3. COITÉ '!D157+'4. VALENTE '!D139 -> 48786.8 | E4: ='1. SANTA LUZ'!E163+'2. RIAÇHÃO'!E4+'3. COITÉ '!E157+'4. VALENTE '!E139 -> 56800.98 | F4: ='1. SANTA LUZ'!F163+'2. RIAÇHÃO'!F4+'3. COITÉ '!F157+'4. VALENTE '!F139 -> 53718.63 | G4: ='1. SANTA LUZ'!G163+'2. RIAÇHÃO'!G4+'3. COITÉ '!G157+'4. VALENTE '!G139 -> 44404.22 | H4: ='1. SANTA LUZ'!H163+'2. RIAÇHÃO'!H4+'3. COITÉ '!H157+'4. VALENTE '!H139 -> 33499.58 | I4: ='1. SANTA LUZ'!I163+'2. RIAÇHÃO'!I4+'3. COITÉ '!I157+'4. VALENTE '!I139 -> 68230.16 | J4: ='1. SANTA LUZ'!J163+'2. RIAÇHÃO'!J4+'3. COITÉ '!J157+'4. VALENTE '!J139 -> 54263.96 | ... N4: ='1. SANTA LUZ'!N163+'2. RIAÇHÃO'!N4+'3. COITÉ '!N157+'4. VALENTE '!N139 -> 17602.28 | O4: =SUM(C4:N4) -> 613595.27 | U4: =#REF!*1.15 -> #REF!
B5: Particular | C5: ='1. SANTA LUZ'!C164+'2. RIAÇHÃO'!C5+'3. COITÉ '!C158+'4. VALENTE '!C140 -> 72292.62 | D5: ='1. SANTA LUZ'!D164+'2. RIAÇHÃO'!D5+'3. COITÉ '!D158+'4. VALENTE '!D140 -> 61022.05 | E5: ='1. SANTA LUZ'!E164+'2. RIAÇHÃO'!E5+'3. COITÉ '!E158+'4. VALENTE '!E140 -> 73966.85 | F5: ='1. SANTA LUZ'!F164+'2. RIAÇHÃO'!F5+'3. COITÉ '!F158+'4. VALENTE '!F140 -> 72940.19 | G5: ='1. SANTA LUZ'!G164+'2. RIAÇHÃO'!G5+'3. COITÉ '!G158+'4. VALENTE '!G140 -> 87288.02 | H5: ='1. SANTA LUZ'!H164+'2. RIAÇHÃO'!H5+'3. COITÉ '!H158+'4. VALENTE '!H140 -> 68164.38 | I5: ='1. SANTA LUZ'!I164+'2. RIAÇHÃO'!I5+'3. COITÉ '!I158+'4. VALENTE '!I140 -> 81469.18 | J5: ='1. SANTA LUZ'!J164+'2. RIAÇHÃO'!J5+'3. COITÉ '!J158+'4. VALENTE '!J140 -> 106957.63 | ... N5: ='1. SANTA LUZ'!N164+'2. RIAÇHÃO'!N5+'3. COITÉ '!N158+'4. VALENTE '!N140 -> 46175.38 | O5: =SUM(C5:N5) -> 1014892.1
B6: realizado 2025 | C6: ='1. SANTA LUZ'!C165+'2. RIAÇHÃO'!C6+'3. COITÉ '!C159+'4. VALENTE '!C141 -> 124165.67 | D6: ='1. SANTA LUZ'!D165+'2. RIAÇHÃO'!D6+'3. COITÉ '!D159+'4. VALENTE '!D141 -> 109808.85 | E6: ='1. SANTA LUZ'!E165+'2. RIAÇHÃO'!E6+'3. COITÉ '!E159+'4. VALENTE '!E141 -> 130767.83 | F6: ='1. SANTA LUZ'!F165+'2. RIAÇHÃO'!F6+'3. COITÉ '!F159+'4. VALENTE '!F141 -> 126658.82 | G6: ='1. SANTA LUZ'!G165+'2. RIAÇHÃO'!G6+'3. COITÉ '!G159+'4. VALENTE '!G141 -> 138389.31 | H6: ='1. SANTA LUZ'!H165+'2. RIAÇHÃO'!H6+'3. COITÉ '!H159+'4. VALENTE '!H141 -> 109393.88 | I6: ='1. SANTA LUZ'!I165+'2. RIAÇHÃO'!I6+'3. COITÉ '!I159+'4. VALENTE '!I141 -> 160033.67 | J6: ='1. SANTA LUZ'!J165+'2. RIAÇHÃO'!J6+'3. COITÉ '!J159+'4. VALENTE '!J141 -> 168427.59 | ... M6: ='1. SANTA LUZ'!M165+'2. RIAÇHÃO'!M6+'3. COITÉ '!M159+'4. VALENTE '!M141 -> 171787.24 | N6: 118998 | O6: =SUM(C6:N6) -> 1722982.8
B7: cresc a.a | O7: =(O6/#REF!)-1 -> #REF!
B8: % | C8: =(C6/C3)-1 -> 0.12315288 | D8: =(D6/D3)-1 -> -0.044911608 | E8: =(E6/E3)-1 -> 0.15450861 | F8: =(F6/F3)-1 -> -0.028807002 | G8: =(G6/G3)-1 -> -0.020104162 | H8: =(H6/H3)-1 -> -0.088385689 | I8: =(I6/I3)-1 -> 0.24210095 | J8: =(J6/J3)-1 -> 0.11806809 | ... N8: =(N6/N3)-1 -> -0.0025283899 | O8: =O6/O3 -> 1.0856966
B10: BONUS | C10: =(3300)+(2000*C8) -> 3546.3058 | D10: 3000 | E10: =(3300)+(2000*E8) -> 3609.0172 | F10: 3000 | G10: 3000 | H10: 2500 | I10: =(3300)+(2000*I8) -> 3784.2019 | J10: =(3300)+(2000*J8) -> 3536.1362 | K10: =(3300)+(2000*K8) -> 3858.3587 | L10: =(3300)+(2000*L8) -> 3709.3588 | M10: =(3300)+(2000*M8) -> 3404.8458 | N10: 3000 | O10: =SUM(C10:N10) -> 39948.224 | P10: TOTAL ANO/ LIDERANÇA
O11: =SUM('1. SANTA LUZ'!M211+'3. COITÉ '!M204+'4. VALENTE '!M184) -> 3215.8897 | P11: TOTAL BALCÃO
B12: 2026 | C12: JAN | D12: FEV | E12: MAR | F12: ABR | G12: MAI | H12: JUN | I12: JUL | J12: AGO | K12: SET | L12: OUT | M12: NOV | N12: DEZ
B13: meta 2026 | C13: ='1. SANTA LUZ'!C339+'3. COITÉ '!C285+'4. VALENTE '!C265 -> 152000 | D13: ='1. SANTA LUZ'!D339+'3. COITÉ '!D285+'4. VALENTE '!D265 -> 145000 | E13: ='1. SANTA LUZ'!E339+'3. COITÉ '!E285+'4. VALENTE '!E265 -> 160000 | F13: ='1. SANTA LUZ'!F339+'3. COITÉ '!F285+'4. VALENTE '!F265 -> 155000 | G13: ='1. SANTA LUZ'!G339+'3. COITÉ '!G285+'4. VALENTE '!G265 -> 171059.34 | H13: ='1. SANTA LUZ'!H339+'3. COITÉ '!H285+'4. VALENTE '!H265 -> 134000 | I13: ='1. SANTA LUZ'!I339+'3. COITÉ '!I285+'4. VALENTE '!I265 -> 180412.21 | J13: ='1. SANTA LUZ'!J339+'3. COITÉ '!J285+'4. VALENTE '!J265 -> 189744.24 | ... N13: ='1. SANTA LUZ'!N339+'3. COITÉ '!N285+'4. VALENTE '!N265 -> 120693.93 | O13: =SUM(C13:N13) -> 2012468.7
B14: Particular | C14: 84442.38 | D14: ='1. SANTA LUZ'!D342+'3. COITÉ '!D288+'4. VALENTE '!D268 -> 0 | E14: ='1. SANTA LUZ'!E342+'3. COITÉ '!E288+'4. VALENTE '!E268 -> 0 | F14: ='1. SANTA LUZ'!F342+'3. COITÉ '!F288+'4. VALENTE '!F268 -> 0 | G14: ='1. SANTA LUZ'!G342+'3. COITÉ '!G288+'4. VALENTE '!G268 -> 0 | H14: ='1. SANTA LUZ'!H342+'3. COITÉ '!H288+'4. VALENTE '!H268 -> 0 | I14: ='1. SANTA LUZ'!I342+'3. COITÉ '!I288+'4. VALENTE '!I268 -> 0 | J14: ='1. SANTA LUZ'!J342+'3. COITÉ '!J288+'4. VALENTE '!J268 -> 0 | K14: ='1. SANTA LUZ'!K342+'3. COITÉ '!K288+'4. VALENTE '!K268 -> 0 | ... N14: ='1. SANTA LUZ'!N342+'3. COITÉ '!N288+'4. VALENTE '!N268 -> 0 | O14: =SUM(C14:N14) -> 84442.38
B15: Convênio | C15: 62547.39 | D15: ='1. SANTA LUZ'!D344+'3. COITÉ '!D287+'4. VALENTE '!D267 -> 0 | E15: ='1. SANTA LUZ'!E344+'3. COITÉ '!E287+'4. VALENTE '!E267 -> 0 | F15: ='1. SANTA LUZ'!F344+'3. COITÉ '!F287+'4. VALENTE '!F267 -> 0 | G15: ='1. SANTA LUZ'!G344+'3. COITÉ '!G287+'4. VALENTE '!G267 -> 0 | H15: ='1. SANTA LUZ'!H344+'3. COITÉ '!H287+'4. VALENTE '!H267 -> 0 | I15: ='1. SANTA LUZ'!I344+'3. COITÉ '!I287+'4. VALENTE '!I267 -> 0 | J15: ='1. SANTA LUZ'!J344+'3. COITÉ '!J287+'4. VALENTE '!J267 -> 0 | K15: ='1. SANTA LUZ'!K344+'3. COITÉ '!K287+'4. VALENTE '!K267 -> 0 | ... N15: ='1. SANTA LUZ'!N344+'3. COITÉ '!N287+'4. VALENTE '!N267 -> 0 | O15: =SUM(C15:N15) -> 62547.39 | U15: =#REF!*1.15 -> #REF!
B16: realizado 2026 | C16: ='1. SANTA LUZ'!C351+'3. COITÉ '!C289+'4. VALENTE '!C269 -> 146989.77 | D16: ='1. SANTA LUZ'!D341+'3. COITÉ '!D289+'4. VALENTE '!D269+'2. RIAÇHÃO'!D6 -> 0 | E16: ='1. SANTA LUZ'!E341+'3. COITÉ '!E289+'4. VALENTE '!E269+'2. RIAÇHÃO'!E6 -> 0 | F16: ='1. SANTA LUZ'!F341+'3. COITÉ '!F289+'4. VALENTE '!F269+'2. RIAÇHÃO'!F6 -> 0 | N16: ='1. SANTA LUZ'!N341+'3. COITÉ '!N289+'4. VALENTE '!N269+'2. RIAÇHÃO'!N6 -> 0
B17: cresc a.a | C17: =(C16/C6)-1 -> 0.18381973
B18: meta% | C18: =(C16/C13)-1 -> -0.032962039

Sheet Planilha2
